{
"meta":{"test_sets":[],"test_metrics":[],"learn_metrics":[{"best_value":"Min","name":"MultiClass"}],"launch_mode":"Train","parameters":"","iteration_count":1000,"learn_sets":["learn"],"name":"experiment"},
"iterations":[
{"learn":[2.799558932],"iteration":0,"passed_time":0.190394612,"remaining_time":190.2042174},
{"learn":[2.713915002],"iteration":1,"passed_time":0.2663701491,"remaining_time":132.9187044},
{"learn":[2.642591378],"iteration":2,"passed_time":0.3390029121,"remaining_time":112.6619678},
{"learn":[2.587173831],"iteration":3,"passed_time":0.4064227182,"remaining_time":101.1992568},
{"learn":[2.518257478],"iteration":4,"passed_time":0.4711252969,"remaining_time":93.75393409},
{"learn":[2.474581753],"iteration":5,"passed_time":0.5502316613,"remaining_time":91.15504522},
{"learn":[2.432494885],"iteration":6,"passed_time":0.6228972395,"remaining_time":88.36242268},
{"learn":[2.380983834],"iteration":7,"passed_time":0.6894259907,"remaining_time":85.48882285},
{"learn":[2.332889031],"iteration":8,"passed_time":0.7700400488,"remaining_time":84.78996538},
{"learn":[2.286552353],"iteration":9,"passed_time":0.848775572,"remaining_time":84.02878163},
{"learn":[2.249310402],"iteration":10,"passed_time":0.9243484137,"remaining_time":83.10732556},
{"learn":[2.215820649],"iteration":11,"passed_time":0.9840028882,"remaining_time":81.01623779},
{"learn":[2.182108937],"iteration":12,"passed_time":1.049639851,"remaining_time":79.69188712},
{"learn":[2.151134341],"iteration":13,"passed_time":1.117630059,"remaining_time":78.71308843},
{"learn":[2.119965297],"iteration":14,"passed_time":1.183666308,"remaining_time":77.72742091},
{"learn":[2.093725146],"iteration":15,"passed_time":1.246496307,"remaining_time":76.65952288},
{"learn":[2.07199322],"iteration":16,"passed_time":1.31570809,"remaining_time":76.07888541},
{"learn":[2.04835402],"iteration":17,"passed_time":1.374090641,"remaining_time":74.96427831},
{"learn":[2.026327666],"iteration":18,"passed_time":1.4417352,"remaining_time":74.43906478},
{"learn":[2.00526867],"iteration":19,"passed_time":1.507833767,"remaining_time":73.88385456},
{"learn":[1.985413396],"iteration":20,"passed_time":1.567783009,"remaining_time":73.08855074},
{"learn":[1.964048725],"iteration":21,"passed_time":1.636480993,"remaining_time":72.7490187},
{"learn":[1.945847511],"iteration":22,"passed_time":1.695519814,"remaining_time":72.02273296},
{"learn":[1.926521638],"iteration":23,"passed_time":1.775686245,"remaining_time":72.21124063},
{"learn":[1.911298521],"iteration":24,"passed_time":1.844207516,"remaining_time":71.92409313},
{"learn":[1.887547524],"iteration":25,"passed_time":1.916883766,"remaining_time":71.80941491},
{"learn":[1.87224669],"iteration":26,"passed_time":1.975332957,"remaining_time":71.18514694},
{"learn":[1.855447828],"iteration":27,"passed_time":2.066684606,"remaining_time":71.74347988},
{"learn":[1.835545162],"iteration":28,"passed_time":2.145451463,"remaining_time":71.83563346},
{"learn":[1.819293564],"iteration":29,"passed_time":2.215105558,"remaining_time":71.62174637},
{"learn":[1.805591891],"iteration":30,"passed_time":2.277198897,"remaining_time":71.18083004},
{"learn":[1.792781764],"iteration":31,"passed_time":2.353473869,"remaining_time":71.19258455},
{"learn":[1.778006246],"iteration":32,"passed_time":2.444249984,"remaining_time":71.62393134},
{"learn":[1.76456426],"iteration":33,"passed_time":2.52287871,"remaining_time":71.67943628},
{"learn":[1.752801626],"iteration":34,"passed_time":2.584733341,"remaining_time":71.26479069},
{"learn":[1.739903723],"iteration":35,"passed_time":2.653629044,"remaining_time":71.05828884},
{"learn":[1.727510258],"iteration":36,"passed_time":2.723002335,"remaining_time":70.87165536},
{"learn":[1.714829153],"iteration":37,"passed_time":2.804210836,"remaining_time":70.99081116},
{"learn":[1.703040265],"iteration":38,"passed_time":2.898071598,"remaining_time":71.41145655},
{"learn":[1.691127167],"iteration":39,"passed_time":2.969584807,"remaining_time":71.27003536},
{"learn":[1.680495868],"iteration":40,"passed_time":3.04002152,"remaining_time":71.10684482},
{"learn":[1.666550446],"iteration":41,"passed_time":3.134489008,"remaining_time":71.49620165},
{"learn":[1.657923216],"iteration":42,"passed_time":3.218411304,"remaining_time":71.62836321},
{"learn":[1.650202706],"iteration":43,"passed_time":3.277207278,"remaining_time":71.20477632},
{"learn":[1.641368339],"iteration":44,"passed_time":3.346793931,"remaining_time":71.02640454},
{"learn":[1.629384794],"iteration":45,"passed_time":3.416796794,"remaining_time":70.86139438},
{"learn":[1.619848846],"iteration":46,"passed_time":3.46853826,"remaining_time":70.33014812},
{"learn":[1.610339499],"iteration":47,"passed_time":3.520306599,"remaining_time":69.81941422},
{"learn":[1.602352751],"iteration":48,"passed_time":3.566761137,"remaining_time":69.22428247},
{"learn":[1.593110445],"iteration":49,"passed_time":3.619290566,"remaining_time":68.76652076},
{"learn":[1.580821161],"iteration":50,"passed_time":3.6646408,"remaining_time":68.19106116},
{"learn":[1.573602559],"iteration":51,"passed_time":3.721639179,"remaining_time":67.84834503},
{"learn":[1.56379109],"iteration":52,"passed_time":3.778309099,"remaining_time":67.51054182},
{"learn":[1.553024431],"iteration":53,"passed_time":3.837111636,"remaining_time":67.22051125},
{"learn":[1.547014638],"iteration":54,"passed_time":3.884847931,"remaining_time":66.74875081},
{"learn":[1.535814489],"iteration":55,"passed_time":3.935324109,"remaining_time":66.3383207},
{"learn":[1.525494783],"iteration":56,"passed_time":3.97902326,"remaining_time":65.82840236},
{"learn":[1.517945982],"iteration":57,"passed_time":4.04513848,"remaining_time":65.69862841},
{"learn":[1.512198323],"iteration":58,"passed_time":4.083002203,"remaining_time":65.12042496},
{"learn":[1.505463485],"iteration":59,"passed_time":4.144079284,"remaining_time":64.92390879},
{"learn":[1.495190258],"iteration":60,"passed_time":4.192871142,"remaining_time":64.54272135},
{"learn":[1.488962759],"iteration":61,"passed_time":4.236772397,"remaining_time":64.09826627},
{"learn":[1.482844226],"iteration":62,"passed_time":4.291832441,"remaining_time":63.83249201},
{"learn":[1.477389596],"iteration":63,"passed_time":4.342152697,"remaining_time":63.5039832},
{"learn":[1.471017553],"iteration":64,"passed_time":4.393527907,"remaining_time":63.19920912},
{"learn":[1.462411602],"iteration":65,"passed_time":4.442318669,"remaining_time":62.86553995},
{"learn":[1.455890422],"iteration":66,"passed_time":4.497885396,"remaining_time":62.63473246},
{"learn":[1.450945023],"iteration":67,"passed_time":4.543458741,"remaining_time":62.27211098},
{"learn":[1.44358273],"iteration":68,"passed_time":4.596441317,"remaining_time":62.01865024},
{"learn":[1.435376986],"iteration":69,"passed_time":4.646813225,"remaining_time":61.73623284},
{"learn":[1.428676423],"iteration":70,"passed_time":4.695612354,"remaining_time":61.43977292},
{"learn":[1.421072263],"iteration":71,"passed_time":4.752755051,"remaining_time":61.25773177},
{"learn":[1.415775787],"iteration":72,"passed_time":4.809042181,"remaining_time":61.06824797},
{"learn":[1.410763642],"iteration":73,"passed_time":4.856282824,"remaining_time":60.76916074},
{"learn":[1.405896759],"iteration":74,"passed_time":4.909067557,"remaining_time":60.54516654},
{"learn":[1.399046346],"iteration":75,"passed_time":4.956055988,"remaining_time":60.25520702},
{"learn":[1.390308341],"iteration":76,"passed_time":5.007095288,"remaining_time":60.02011625},
{"learn":[1.383818952],"iteration":77,"passed_time":5.059372261,"remaining_time":59.80437468},
{"learn":[1.377771797],"iteration":78,"passed_time":5.108061654,"remaining_time":59.55094662},
{"learn":[1.366052558],"iteration":79,"passed_time":5.161961054,"remaining_time":59.36255212},
{"learn":[1.359226838],"iteration":80,"passed_time":5.213638032,"remaining_time":59.1522636},
{"learn":[1.350015745],"iteration":81,"passed_time":5.266620953,"remaining_time":58.96046384},
{"learn":[1.343105143],"iteration":82,"passed_time":5.320669422,"remaining_time":58.78378145},
{"learn":[1.336924514],"iteration":83,"passed_time":5.462191402,"remaining_time":59.56389672},
{"learn":[1.330665787],"iteration":84,"passed_time":5.541936146,"remaining_time":59.65731263},
{"learn":[1.325749765],"iteration":85,"passed_time":5.59640925,"remaining_time":59.47811691},
{"learn":[1.320722705],"iteration":86,"passed_time":5.651129162,"remaining_time":59.30437845},
{"learn":[1.316532435],"iteration":87,"passed_time":5.702098601,"remaining_time":59.09447641},
{"learn":[1.309783996],"iteration":88,"passed_time":5.771968109,"remaining_time":59.08160615},
{"learn":[1.304086287],"iteration":89,"passed_time":5.825141651,"remaining_time":58.89865447},
{"learn":[1.300527602],"iteration":90,"passed_time":5.879158223,"remaining_time":58.7269761},
{"learn":[1.29485196],"iteration":91,"passed_time":5.933560781,"remaining_time":58.5616651},
{"learn":[1.288654157],"iteration":92,"passed_time":5.987484706,"remaining_time":58.39407128},
{"learn":[1.282293584],"iteration":93,"passed_time":6.048436399,"remaining_time":58.29663168},
{"learn":[1.276088395],"iteration":94,"passed_time":6.103641153,"remaining_time":58.14521309},
{"learn":[1.271073647],"iteration":95,"passed_time":6.158876433,"remaining_time":57.99608641},
{"learn":[1.264762505],"iteration":96,"passed_time":6.212527893,"remaining_time":57.83415141},
{"learn":[1.258404711],"iteration":97,"passed_time":6.275236146,"remaining_time":57.75778576},
{"learn":[1.25352676],"iteration":98,"passed_time":6.330603265,"remaining_time":57.61488426},
{"learn":[1.250564052],"iteration":99,"passed_time":6.388078785,"remaining_time":57.49270907},
{"learn":[1.244763841],"iteration":100,"passed_time":6.444878965,"remaining_time":57.36580385},
{"learn":[1.239314427],"iteration":101,"passed_time":6.496268504,"remaining_time":57.19263839},
{"learn":[1.233409545],"iteration":102,"passed_time":6.551984484,"remaining_time":57.05951536},
{"learn":[1.228246337],"iteration":103,"passed_time":6.605892028,"remaining_time":56.91230055},
{"learn":[1.224653969],"iteration":104,"passed_time":6.661929075,"remaining_time":56.78501449},
{"learn":[1.217514102],"iteration":105,"passed_time":6.718588572,"remaining_time":56.66432248},
{"learn":[1.213777114],"iteration":106,"passed_time":6.773543225,"remaining_time":56.53059906},
{"learn":[1.206395557],"iteration":107,"passed_time":6.832342409,"remaining_time":56.43008731},
{"learn":[1.201067983],"iteration":108,"passed_time":6.887550997,"remaining_time":56.30099026},
{"learn":[1.197091894],"iteration":109,"passed_time":6.938748482,"remaining_time":56.14078317},
{"learn":[1.192562173],"iteration":110,"passed_time":6.985680267,"remaining_time":55.9483762},
{"learn":[1.188839801],"iteration":111,"passed_time":7.048468554,"remaining_time":55.8842864},
{"learn":[1.184241523],"iteration":112,"passed_time":7.108971093,"remaining_time":55.80227752},
{"learn":[1.177345944],"iteration":113,"passed_time":7.165362781,"remaining_time":55.6886967},
{"learn":[1.170193365],"iteration":114,"passed_time":7.220819042,"remaining_time":55.56891176},
{"learn":[1.164727861],"iteration":115,"passed_time":7.274281302,"remaining_time":55.43504027},
{"learn":[1.161480353],"iteration":116,"passed_time":7.328617088,"remaining_time":55.3091358},
{"learn":[1.157193781],"iteration":117,"passed_time":7.387843114,"remaining_time":55.22099684},
{"learn":[1.149962437],"iteration":118,"passed_time":7.443023405,"remaining_time":55.10339176},
{"learn":[1.145243662],"iteration":119,"passed_time":7.499499894,"remaining_time":54.99633256},
{"learn":[1.141202336],"iteration":120,"passed_time":7.549811838,"remaining_time":54.84532732},
{"learn":[1.137754257],"iteration":121,"passed_time":7.604155593,"remaining_time":54.72498862},
{"learn":[1.13442144],"iteration":122,"passed_time":7.654012326,"remaining_time":54.57373016},
{"learn":[1.127234467],"iteration":123,"passed_time":7.712084935,"remaining_time":54.48214841},
{"learn":[1.119544121],"iteration":124,"passed_time":7.763988786,"remaining_time":54.3479215},
{"learn":[1.115055681],"iteration":125,"passed_time":7.897019388,"remaining_time":54.77773766},
{"learn":[1.11167614],"iteration":126,"passed_time":7.974508356,"remaining_time":54.81689603},
{"learn":[1.105143785],"iteration":127,"passed_time":8.027450877,"remaining_time":54.6870091},
{"learn":[1.099550185],"iteration":128,"passed_time":8.080333576,"remaining_time":54.5579112},
{"learn":[1.093938951],"iteration":129,"passed_time":8.137281611,"remaining_time":54.45719232},
{"learn":[1.088154866],"iteration":130,"passed_time":8.189497572,"remaining_time":54.32575107},
{"learn":[1.084845016],"iteration":131,"passed_time":8.239779866,"remaining_time":54.18279487},
{"learn":[1.077661128],"iteration":132,"passed_time":8.289357696,"remaining_time":54.03664002},
{"learn":[1.073344635],"iteration":133,"passed_time":8.348052196,"remaining_time":53.95084479},
{"learn":[1.066032878],"iteration":134,"passed_time":8.404078992,"remaining_time":53.84835799},
{"learn":[1.061625186],"iteration":135,"passed_time":8.458072359,"remaining_time":53.73363617},
{"learn":[1.057964248],"iteration":136,"passed_time":8.509371689,"remaining_time":53.60283042},
{"learn":[1.053568082],"iteration":137,"passed_time":8.559299186,"remaining_time":53.46460796},
{"learn":[1.052399524],"iteration":138,"passed_time":8.612816303,"remaining_time":53.34989091},
{"learn":[1.046991469],"iteration":139,"passed_time":8.668625243,"remaining_time":53.25012649},
{"learn":[1.043076953],"iteration":140,"passed_time":8.72756181,"remaining_time":53.17003968},
{"learn":[1.040862253],"iteration":141,"passed_time":8.784139029,"remaining_time":53.07599498},
{"learn":[1.037614112],"iteration":142,"passed_time":8.833550856,"remaining_time":52.93953205},
{"learn":[1.035210749],"iteration":143,"passed_time":8.885929255,"remaining_time":52.8219128},
{"learn":[1.032026539],"iteration":144,"passed_time":8.940419208,"remaining_time":52.7176443},
{"learn":[1.027738268],"iteration":145,"passed_time":8.995830933,"remaining_time":52.61944943},
{"learn":[1.024054222],"iteration":146,"passed_time":9.053728892,"remaining_time":52.53626357},
{"learn":[1.020893534],"iteration":147,"passed_time":9.109359791,"remaining_time":52.44036853},
{"learn":[1.014444469],"iteration":148,"passed_time":9.159753583,"remaining_time":52.31510268},
{"learn":[1.012088717],"iteration":149,"passed_time":9.208709078,"remaining_time":52.18268477},
{"learn":[1.01006124],"iteration":150,"passed_time":9.271186957,"remaining_time":52.12740216},
{"learn":[1.0071466],"iteration":151,"passed_time":9.32086734,"remaining_time":52.00062832},
{"learn":[1.004989832],"iteration":152,"passed_time":9.378060314,"remaining_time":51.91645154},
{"learn":[1.002652327],"iteration":153,"passed_time":9.433787688,"remaining_time":51.82457392},
{"learn":[1.000083155],"iteration":154,"passed_time":9.487852439,"remaining_time":51.72409878},
{"learn":[0.9970477752],"iteration":155,"passed_time":9.536574461,"remaining_time":51.59531311},
{"learn":[0.9936378402],"iteration":156,"passed_time":9.586825714,"remaining_time":51.47575845},
{"learn":[0.9884679871],"iteration":157,"passed_time":9.642258793,"remaining_time":51.38469559},
{"learn":[0.9847089961],"iteration":158,"passed_time":9.696484083,"remaining_time":51.28769254},
{"learn":[0.9824390193],"iteration":159,"passed_time":9.748436654,"remaining_time":51.17929243},
{"learn":[0.9791526927],"iteration":160,"passed_time":9.793357454,"remaining_time":51.03494971},
{"learn":[0.9766937885],"iteration":161,"passed_time":9.84523876,"remaining_time":50.92784},
{"learn":[0.9703505223],"iteration":162,"passed_time":9.89438083,"remaining_time":50.80734205},
{"learn":[0.9685509826],"iteration":163,"passed_time":9.943559929,"remaining_time":50.68790305},
{"learn":[0.9677315003],"iteration":164,"passed_time":9.995219887,"remaining_time":50.58187034},
{"learn":[0.9620479012],"iteration":165,"passed_time":10.045991,"remaining_time":50.47202708},
{"learn":[0.9589079584],"iteration":166,"passed_time":10.10127239,"remaining_time":50.38538861},
{"learn":[0.9552089872],"iteration":167,"passed_time":10.14913705,"remaining_time":50.262393},
{"learn":[0.9505290592],"iteration":168,"passed_time":10.20010449,"remaining_time":50.1555434},
{"learn":[0.9482428073],"iteration":169,"passed_time":10.24503392,"remaining_time":50.01987147},
{"learn":[0.9431222082],"iteration":170,"passed_time":10.29573349,"remaining_time":49.91323428},
{"learn":[0.9394875268],"iteration":171,"passed_time":10.35279411,"remaining_time":49.83786932},
{"learn":[0.9367235418],"iteration":172,"passed_time":10.39818696,"remaining_time":49.70693997},
{"learn":[0.9324568822],"iteration":173,"passed_time":10.45154638,"remaining_time":49.61481212},
{"learn":[0.9289082373],"iteration":174,"passed_time":10.49585847,"remaining_time":49.48047566},
{"learn":[0.9271525607],"iteration":175,"passed_time":10.55110993,"remaining_time":49.39837832},
{"learn":[0.9250225759],"iteration":176,"passed_time":10.60078754,"remaining_time":49.29066748},
{"learn":[0.9215637202],"iteration":177,"passed_time":10.65210846,"remaining_time":49.19119748},
{"learn":[0.9185740653],"iteration":178,"passed_time":10.7071301,"remaining_time":49.10923916},
{"learn":[0.9158474248],"iteration":179,"passed_time":10.76564813,"remaining_time":49.04350814},
{"learn":[0.9128535246],"iteration":180,"passed_time":10.81523133,"remaining_time":48.93742793},
{"learn":[0.9076662223],"iteration":181,"passed_time":10.86505467,"remaining_time":48.83304793},
{"learn":[0.9044527049],"iteration":182,"passed_time":10.91527638,"remaining_time":48.73104264},
{"learn":[0.9000991373],"iteration":183,"passed_time":10.96735953,"remaining_time":48.63785532},
{"learn":[0.8985598857],"iteration":184,"passed_time":11.01785562,"remaining_time":48.53812072},
{"learn":[0.8954750754],"iteration":185,"passed_time":11.07350993,"remaining_time":48.46148971},
{"learn":[0.8921567086],"iteration":186,"passed_time":11.12334864,"remaining_time":48.35979918},
{"learn":[0.8890239508],"iteration":187,"passed_time":11.17177398,"remaining_time":48.25255568},
{"learn":[0.8857571817],"iteration":188,"passed_time":11.21942247,"remaining_time":48.1426012},
{"learn":[0.8844991331],"iteration":189,"passed_time":11.26844137,"remaining_time":48.03914481},
{"learn":[0.8828418577],"iteration":190,"passed_time":11.32356405,"remaining_time":47.9621116},
{"learn":[0.8809220683],"iteration":191,"passed_time":11.37289446,"remaining_time":47.86093085},
{"learn":[0.8785314118],"iteration":192,"passed_time":11.42321302,"remaining_time":47.76441922},
{"learn":[0.8757230075],"iteration":193,"passed_time":11.47229867,"remaining_time":47.66326147},
{"learn":[0.8746338297],"iteration":194,"passed_time":11.53189818,"remaining_time":47.6060412},
{"learn":[0.8710597303],"iteration":195,"passed_time":11.57711814,"remaining_time":47.48981115},
{"learn":[0.8679569245],"iteration":196,"passed_time":11.62867679,"remaining_time":47.40013939},
{"learn":[0.8645655402],"iteration":197,"passed_time":11.68126014,"remaining_time":47.31500318},
{"learn":[0.8618432471],"iteration":198,"passed_time":11.73695433,"remaining_time":47.24271569},
{"learn":[0.8603050299],"iteration":199,"passed_time":11.78445887,"remaining_time":47.13783549},
{"learn":[0.8557946685],"iteration":200,"passed_time":11.8422586,"remaining_time":47.07445085},
{"learn":[0.8537310192],"iteration":201,"passed_time":11.89130857,"remaining_time":46.97655564},
{"learn":[0.8511051751],"iteration":202,"passed_time":11.94191884,"remaining_time":46.88526755},
{"learn":[0.8493890098],"iteration":203,"passed_time":11.99117929,"remaining_time":46.78911134},
{"learn":[0.8466347536],"iteration":204,"passed_time":12.04211462,"remaining_time":46.69990791},
{"learn":[0.8448987334],"iteration":205,"passed_time":12.09541695,"remaining_time":46.62019933},
{"learn":[0.843290292],"iteration":206,"passed_time":12.1476811,"remaining_time":46.53676867},
{"learn":[0.8393724845],"iteration":207,"passed_time":12.19704804,"remaining_time":46.442606},
{"learn":[0.8375758472],"iteration":208,"passed_time":12.24767192,"remaining_time":46.35362915},
{"learn":[0.8341567318],"iteration":209,"passed_time":12.29255799,"remaining_time":46.24343244},
{"learn":[0.8302310488],"iteration":210,"passed_time":12.34878485,"remaining_time":46.17626182},
{"learn":[0.8283837521],"iteration":211,"passed_time":12.40042933,"remaining_time":46.09216186},
{"learn":[0.8256478275],"iteration":212,"passed_time":12.45065033,"remaining_time":46.00310707},
{"learn":[0.8236782077],"iteration":213,"passed_time":12.50807698,"remaining_time":45.94088087},
{"learn":[0.8211498405],"iteration":214,"passed_time":12.56061768,"remaining_time":45.86085989},
{"learn":[0.8188826365],"iteration":215,"passed_time":12.62006369,"remaining_time":45.8061571},
{"learn":[0.817013602],"iteration":216,"passed_time":12.68116555,"remaining_time":45.75738538},
{"learn":[0.8155415006],"iteration":217,"passed_time":12.702836,"remaining_time":45.56705392},
{"learn":[0.8143229118],"iteration":218,"passed_time":12.75748885,"remaining_time":45.49588491},
{"learn":[0.8118248398],"iteration":219,"passed_time":12.81024069,"remaining_time":45.4181261},
{"learn":[0.81055611],"iteration":220,"passed_time":12.95952741,"remaining_time":45.6808681},
{"learn":[0.8090853587],"iteration":221,"passed_time":13.01172781,"remaining_time":45.59965873},
{"learn":[0.8078850752],"iteration":222,"passed_time":13.06636329,"remaining_time":45.52719405},
{"learn":[0.8061325984],"iteration":223,"passed_time":13.13501212,"remaining_time":45.50343484},
{"learn":[0.8046214716],"iteration":224,"passed_time":13.18819064,"remaining_time":45.42598997},
{"learn":[0.8040300184],"iteration":225,"passed_time":13.24185837,"remaining_time":45.3504353},
{"learn":[0.803180356],"iteration":226,"passed_time":13.2983388,"remaining_time":45.28465152},
{"learn":[0.8004272406],"iteration":227,"passed_time":13.35297984,"remaining_time":45.21272121},
{"learn":[0.7984538645],"iteration":228,"passed_time":13.40545006,"remaining_time":45.13363318},
{"learn":[0.7963327534],"iteration":229,"passed_time":13.46140709,"remaining_time":45.06644984},
{"learn":[0.7937172865],"iteration":230,"passed_time":13.51128159,"remaining_time":44.97911492},
{"learn":[0.7913156001],"iteration":231,"passed_time":13.56524772,"remaining_time":44.90564762},
{"learn":[0.7897013109],"iteration":232,"passed_time":13.62309681,"remaining_time":44.84512985},
{"learn":[0.7873632325],"iteration":233,"passed_time":13.67807784,"remaining_time":44.77524625},
{"learn":[0.7868264153],"iteration":234,"passed_time":13.7065713,"remaining_time":44.61926401},
{"learn":[0.7822654047],"iteration":235,"passed_time":13.76157548,"remaining_time":44.55018504},
{"learn":[0.7808734627],"iteration":236,"passed_time":13.81151464,"remaining_time":44.46491842},
{"learn":[0.7784689609],"iteration":237,"passed_time":13.86316585,"remaining_time":44.38543015},
{"learn":[0.7751820022],"iteration":238,"passed_time":13.91539737,"remaining_time":44.3080226},
{"learn":[0.7742693328],"iteration":239,"passed_time":13.96928616,"remaining_time":44.23607285},
{"learn":[0.7736299742],"iteration":240,"passed_time":14.01989384,"remaining_time":44.15393953},
{"learn":[0.7710891654],"iteration":241,"passed_time":14.07686097,"remaining_time":44.09198603},
{"learn":[0.769279971],"iteration":242,"passed_time":14.12896631,"remaining_time":44.01492798},
{"learn":[0.7656041344],"iteration":243,"passed_time":14.17940854,"remaining_time":43.93292156},
{"learn":[0.7647407125],"iteration":244,"passed_time":14.23287643,"remaining_time":43.86049675},
{"learn":[0.7630357533],"iteration":245,"passed_time":14.28830673,"remaining_time":43.79424097},
{"learn":[0.761568231],"iteration":246,"passed_time":14.33882813,"remaining_time":43.71310762},
{"learn":[0.7599189321],"iteration":247,"passed_time":14.39205376,"remaining_time":43.64042108},
{"learn":[0.7586007839],"iteration":248,"passed_time":14.4440144,"remaining_time":43.56407555},
{"learn":[0.754670367],"iteration":249,"passed_time":14.49257552,"remaining_time":43.47772655},
{"learn":[0.75305644],"iteration":250,"passed_time":14.54447535,"remaining_time":43.40164158},
{"learn":[0.7502750532],"iteration":251,"passed_time":14.59711888,"remaining_time":43.32795603},
{"learn":[0.7485616212],"iteration":252,"passed_time":14.65042944,"remaining_time":43.25640628},
{"learn":[0.7453730904],"iteration":253,"passed_time":14.70794339,"remaining_time":43.19734554},
{"learn":[0.7436153485],"iteration":254,"passed_time":14.76199853,"remaining_time":43.12819177},
{"learn":[0.7417993994],"iteration":255,"passed_time":14.8107563,"remaining_time":43.0437605},
{"learn":[0.7391654652],"iteration":256,"passed_time":14.8589917,"remaining_time":42.95809662},
{"learn":[0.7375579303],"iteration":257,"passed_time":14.91716047,"remaining_time":42.90129095},
{"learn":[0.7346669551],"iteration":258,"passed_time":14.97516945,"remaining_time":42.84401761},
{"learn":[0.7322072364],"iteration":259,"passed_time":15.02456696,"remaining_time":42.76222904},
{"learn":[0.7301160507],"iteration":260,"passed_time":15.07664576,"remaining_time":42.68828052},
{"learn":[0.7295529344],"iteration":261,"passed_time":15.12509065,"remaining_time":42.60426298},
{"learn":[0.7274525016],"iteration":262,"passed_time":15.1751233,"remaining_time":42.52496528},
{"learn":[0.7265445954],"iteration":263,"passed_time":15.22627519,"remaining_time":42.44900963},
{"learn":[0.7260194614],"iteration":264,"passed_time":15.27996085,"remaining_time":42.38026877},
{"learn":[0.7233978506],"iteration":265,"passed_time":15.33157383,"remaining_time":42.30592178},
{"learn":[0.7211882426],"iteration":266,"passed_time":15.38385338,"remaining_time":42.23357501},
{"learn":[0.7197735258],"iteration":267,"passed_time":15.4335355,"remaining_time":42.15428354},
{"learn":[0.7184628258],"iteration":268,"passed_time":15.47731649,"remaining_time":42.05917603},
{"learn":[0.7168775862],"iteration":269,"passed_time":15.5411845,"remaining_time":42.01875809},
{"learn":[0.7143743151],"iteration":270,"passed_time":15.59052623,"remaining_time":41.93909087},
{"learn":[0.713258454],"iteration":271,"passed_time":15.64191137,"remaining_time":41.86511572},
{"learn":[0.7109627496],"iteration":272,"passed_time":15.69589782,"remaining_time":41.79823339},
{"learn":[0.7096429319],"iteration":273,"passed_time":15.747034,"remaining_time":41.72389301},
{"learn":[0.70754056],"iteration":274,"passed_time":15.79092553,"remaining_time":41.63062185},
{"learn":[0.7066473248],"iteration":275,"passed_time":15.84370077,"remaining_time":41.56101216},
{"learn":[0.705474731],"iteration":276,"passed_time":15.89540276,"remaining_time":41.48872272},
{"learn":[0.7044414272],"iteration":277,"passed_time":15.94427374,"remaining_time":41.40922893},
{"learn":[0.7012059929],"iteration":278,"passed_time":16.00419783,"remaining_time":41.35851841},
{"learn":[0.6998432607],"iteration":279,"passed_time":16.05422694,"remaining_time":41.28229784},
{"learn":[0.696468947],"iteration":280,"passed_time":16.10195435,"remaining_time":41.2003743},
{"learn":[0.6941742441],"iteration":281,"passed_time":16.15566327,"remaining_time":41.13392278},
{"learn":[0.6926151746],"iteration":282,"passed_time":16.20368238,"remaining_time":41.05314582},
{"learn":[0.690889503],"iteration":283,"passed_time":16.27641467,"remaining_time":41.03490459},
{"learn":[0.688714396],"iteration":284,"passed_time":16.32192698,"remaining_time":40.94799224},
{"learn":[0.6862185751],"iteration":285,"passed_time":16.37653842,"remaining_time":40.88408544},
{"learn":[0.6850906816],"iteration":286,"passed_time":16.42554358,"remaining_time":40.80631559},
{"learn":[0.6835654149],"iteration":287,"passed_time":16.47557741,"remaining_time":40.73128861},
{"learn":[0.6812286907],"iteration":288,"passed_time":16.58255082,"remaining_time":40.79651777},
{"learn":[0.6800085037],"iteration":289,"passed_time":16.66423175,"remaining_time":40.79863635},
{"learn":[0.6779370423],"iteration":290,"passed_time":16.72228986,"remaining_time":40.74262376},
{"learn":[0.6765569345],"iteration":291,"passed_time":16.76587941,"remaining_time":40.65151582},
{"learn":[0.6756877852],"iteration":292,"passed_time":16.82026593,"remaining_time":40.58678502},
{"learn":[0.6741602212],"iteration":293,"passed_time":16.87020225,"remaining_time":40.51143805},
{"learn":[0.6725612795],"iteration":294,"passed_time":16.92247335,"remaining_time":40.44184308},
{"learn":[0.669268185],"iteration":295,"passed_time":16.98216973,"remaining_time":40.3900253},
{"learn":[0.6675840721],"iteration":296,"passed_time":17.03683405,"remaining_time":40.32624357},
{"learn":[0.6671312471],"iteration":297,"passed_time":17.08065006,"remaining_time":40.23696758},
{"learn":[0.6660307462],"iteration":298,"passed_time":17.13293086,"remaining_time":40.16784125},
{"learn":[0.6649752636],"iteration":299,"passed_time":17.18665526,"remaining_time":40.10219561},
{"learn":[0.6620910183],"iteration":300,"passed_time":17.23705772,"remaining_time":40.02891476},
{"learn":[0.6603985579],"iteration":301,"passed_time":17.29119572,"remaining_time":39.96441926},
{"learn":[0.6590906901],"iteration":302,"passed_time":17.34855664,"remaining_time":39.90740587},
{"learn":[0.6573855337],"iteration":303,"passed_time":17.394263,"remaining_time":39.82370738},
{"learn":[0.6554277237],"iteration":304,"passed_time":17.44733025,"remaining_time":39.75703123},
{"learn":[0.6541822263],"iteration":305,"passed_time":17.49642418,"remaining_time":39.68143261},
{"learn":[0.6520432061],"iteration":306,"passed_time":17.54592206,"remaining_time":39.60691853},
{"learn":[0.6515871146],"iteration":307,"passed_time":17.60087563,"remaining_time":39.54482447},
{"learn":[0.6507251619],"iteration":308,"passed_time":17.64683201,"remaining_time":39.4626567},
{"learn":[0.6492759423],"iteration":309,"passed_time":17.69973744,"remaining_time":39.39618978},
{"learn":[0.6471210995],"iteration":310,"passed_time":17.74288514,"remaining_time":39.30819249},
{"learn":[0.6440592349],"iteration":311,"passed_time":17.80826011,"remaining_time":39.26949665},
{"learn":[0.6430287257],"iteration":312,"passed_time":17.85876913,"remaining_time":39.19800125},
{"learn":[0.640757659],"iteration":313,"passed_time":17.90967362,"remaining_time":39.1275035},
{"learn":[0.639791583],"iteration":314,"passed_time":17.96206564,"remaining_time":39.06036497},
{"learn":[0.6375541399],"iteration":315,"passed_time":18.01697325,"remaining_time":38.99876487},
{"learn":[0.6362857625],"iteration":316,"passed_time":18.06757838,"remaining_time":38.92793702},
{"learn":[0.634927308],"iteration":317,"passed_time":18.11690052,"remaining_time":38.85448477},
{"learn":[0.6329943421],"iteration":318,"passed_time":18.17034133,"remaining_time":38.78997633},
{"learn":[0.6314938098],"iteration":319,"passed_time":18.22260547,"remaining_time":38.72303662},
{"learn":[0.6296431703],"iteration":320,"passed_time":18.27357549,"remaining_time":38.65345096},
{"learn":[0.628101501],"iteration":321,"passed_time":18.32521252,"remaining_time":38.58538536},
{"learn":[0.626090433],"iteration":322,"passed_time":18.3726278,"remaining_time":38.50857282},
{"learn":[0.6248263118],"iteration":323,"passed_time":18.42482009,"remaining_time":38.44190858},
{"learn":[0.6229647845],"iteration":324,"passed_time":18.48613902,"remaining_time":38.39428874},
{"learn":[0.6220039685],"iteration":325,"passed_time":18.53827043,"remaining_time":38.32758978},
{"learn":[0.620733749],"iteration":326,"passed_time":18.59509513,"remaining_time":38.27063922},
{"learn":[0.6191388573],"iteration":327,"passed_time":18.64610717,"remaining_time":38.20178054},
{"learn":[0.617723076],"iteration":328,"passed_time":18.69806363,"remaining_time":38.13495652},
{"learn":[0.6162767687],"iteration":329,"passed_time":18.74942767,"remaining_time":38.06701981},
{"learn":[0.6139887801],"iteration":330,"passed_time":18.80061789,"remaining_time":37.99883193},
{"learn":[0.6115368431],"iteration":331,"passed_time":18.85180756,"remaining_time":37.93074533},
{"learn":[0.610568545],"iteration":332,"passed_time":18.90614925,"remaining_time":37.86907371},
{"learn":[0.6096711994],"iteration":333,"passed_time":18.95486794,"remaining_time":37.79623368},
{"learn":[0.6083279643],"iteration":334,"passed_time":19.00998936,"remaining_time":37.73624753},
{"learn":[0.6070366894],"iteration":335,"passed_time":19.06151659,"remaining_time":37.66918754},
{"learn":[0.6049949068],"iteration":336,"passed_time":19.11139993,"remaining_time":37.59898561},
{"learn":[0.6042499424],"iteration":337,"passed_time":19.16244443,"remaining_time":37.53117815},
{"learn":[0.6036367584],"iteration":338,"passed_time":19.20785048,"remaining_time":37.45247542},
{"learn":[0.6025671154],"iteration":339,"passed_time":19.26479892,"remaining_time":37.39637438},
{"learn":[0.6014148831],"iteration":340,"passed_time":19.31891621,"remaining_time":37.33479702},
{"learn":[0.60065526],"iteration":341,"passed_time":19.37111631,"remaining_time":37.26957465},
{"learn":[0.5999735886],"iteration":342,"passed_time":19.42119466,"remaining_time":37.20036411},
{"learn":[0.5993384149],"iteration":343,"passed_time":19.47656403,"remaining_time":37.14135466},
{"learn":[0.5974028683],"iteration":344,"passed_time":19.52803089,"remaining_time":37.0749572},
{"learn":[0.5963895216],"iteration":345,"passed_time":19.58767284,"remaining_time":37.02409838},
{"learn":[0.5951444615],"iteration":346,"passed_time":19.65326224,"remaining_time":36.98438111},
{"learn":[0.5943057102],"iteration":347,"passed_time":19.70798268,"remaining_time":36.92415146},
{"learn":[0.5931513079],"iteration":348,"passed_time":19.77825472,"remaining_time":36.89296224},
{"learn":[0.5911350037],"iteration":349,"passed_time":19.82849982,"remaining_time":36.8243568},
{"learn":[0.5896067984],"iteration":350,"passed_time":19.88221082,"remaining_time":36.76226446},
{"learn":[0.589152017],"iteration":351,"passed_time":19.93296952,"remaining_time":36.6947848},
{"learn":[0.587449554],"iteration":352,"passed_time":19.98620063,"remaining_time":36.63193147},
{"learn":[0.5853960239],"iteration":353,"passed_time":20.03683824,"remaining_time":36.56439972},
{"learn":[0.5846563296],"iteration":354,"passed_time":20.08531495,"remaining_time":36.49303703},
{"learn":[0.5838897844],"iteration":355,"passed_time":20.14080076,"remaining_time":36.43448228},
{"learn":[0.5834173089],"iteration":356,"passed_time":20.19130496,"remaining_time":36.36697225},
{"learn":[0.5825635075],"iteration":357,"passed_time":20.24494185,"remaining_time":36.30517504},
{"learn":[0.5805022246],"iteration":358,"passed_time":20.29761473,"remaining_time":36.24170207},
{"learn":[0.5793743444],"iteration":359,"passed_time":20.34852902,"remaining_time":36.1751627},
{"learn":[0.5781057586],"iteration":360,"passed_time":20.39365529,"remaining_time":36.09846463},
{"learn":[0.5771587406],"iteration":361,"passed_time":20.44682761,"remaining_time":36.03612159},
{"learn":[0.5760491343],"iteration":362,"passed_time":20.5032754,"remaining_time":35.97957694},
{"learn":[0.5753655761],"iteration":363,"passed_time":20.55496833,"remaining_time":35.91472489},
{"learn":[0.5738213528],"iteration":364,"passed_time":20.60510249,"remaining_time":35.8472331},
{"learn":[0.573122678],"iteration":365,"passed_time":20.65800082,"remaining_time":35.78462436},
{"learn":[0.5722282019],"iteration":366,"passed_time":20.70428785,"remaining_time":35.71066541},
{"learn":[0.5715057318],"iteration":367,"passed_time":20.76495719,"remaining_time":35.66155691},
{"learn":[0.5704857146],"iteration":368,"passed_time":20.81575508,"remaining_time":35.59550531},
{"learn":[0.5690899777],"iteration":369,"passed_time":20.87149471,"remaining_time":35.53795044},
{"learn":[0.5664532032],"iteration":370,"passed_time":20.92301671,"remaining_time":35.47325475},
{"learn":[0.5646219706],"iteration":371,"passed_time":20.97621195,"remaining_time":35.41145457},
{"learn":[0.5637750558],"iteration":372,"passed_time":21.02789804,"remaining_time":35.34716373},
{"learn":[0.5626301583],"iteration":373,"passed_time":21.0797787,"remaining_time":35.28326596},
{"learn":[0.5614411155],"iteration":374,"passed_time":21.13736693,"remaining_time":35.22894489},
{"learn":[0.5610646018],"iteration":375,"passed_time":21.18967889,"remaining_time":35.16585007},
{"learn":[0.5604981308],"iteration":376,"passed_time":21.24236773,"remaining_time":35.10343527},
{"learn":[0.5596384796],"iteration":377,"passed_time":21.2936725,"remaining_time":35.03879443},
{"learn":[0.5584163425],"iteration":378,"passed_time":21.34640129,"remaining_time":34.97655726},
{"learn":[0.5576331034],"iteration":379,"passed_time":21.39816461,"remaining_time":34.9127949},
{"learn":[0.5572467416],"iteration":380,"passed_time":21.45291683,"remaining_time":34.8539515},
{"learn":[0.5552368079],"iteration":381,"passed_time":21.50715362,"remaining_time":34.79429565},
{"learn":[0.5543293797],"iteration":382,"passed_time":21.55753137,"remaining_time":34.72845131},
{"learn":[0.5536058103],"iteration":383,"passed_time":21.60914358,"remaining_time":34.66466783},
{"learn":[0.5522272717],"iteration":384,"passed_time":21.65465855,"remaining_time":34.59120782},
{"learn":[0.5514209378],"iteration":385,"passed_time":21.70379003,"remaining_time":34.52364527},
{"learn":[0.5496537855],"iteration":386,"passed_time":21.75547967,"remaining_time":34.46023007},
{"learn":[0.5484654796],"iteration":387,"passed_time":21.80275915,"remaining_time":34.38991907},
{"learn":[0.5474804912],"iteration":388,"passed_time":21.85660487,"remaining_time":34.33004004},
{"learn":[0.5455294263],"iteration":389,"passed_time":21.91084662,"remaining_time":34.27081139},
{"learn":[0.5440943929],"iteration":390,"passed_time":21.97052299,"remaining_time":34.22007289},
{"learn":[0.5428103972],"iteration":391,"passed_time":22.02217682,"remaining_time":34.15684568},
{"learn":[0.5414715531],"iteration":392,"passed_time":22.06908011,"remaining_time":34.08634002},
{"learn":[0.5399662242],"iteration":393,"passed_time":22.11979911,"remaining_time":34.021823},
{"learn":[0.5384330528],"iteration":394,"passed_time":22.17296054,"remaining_time":33.96111677},
{"learn":[0.5372680552],"iteration":395,"passed_time":22.22542442,"remaining_time":33.89938472},
{"learn":[0.536426787],"iteration":396,"passed_time":22.29210252,"remaining_time":33.85928922},
{"learn":[0.535105891],"iteration":397,"passed_time":22.34782344,"remaining_time":33.80248672},
{"learn":[0.5333779672],"iteration":398,"passed_time":22.39800496,"remaining_time":33.73734582},
{"learn":[0.531808438],"iteration":399,"passed_time":22.45214309,"remaining_time":33.67821463},
{"learn":[0.5311976035],"iteration":400,"passed_time":22.50396704,"remaining_time":33.61565151},
{"learn":[0.5303744987],"iteration":401,"passed_time":22.55679832,"remaining_time":33.55464029},
{"learn":[0.5298481558],"iteration":402,"passed_time":22.6103179,"remaining_time":33.4946893},
{"learn":[0.5283160724],"iteration":403,"passed_time":22.66313445,"remaining_time":33.43373299},
{"learn":[0.52677938],"iteration":404,"passed_time":22.71212297,"remaining_time":33.367193},
{"learn":[0.5256489886],"iteration":405,"passed_time":22.76209021,"remaining_time":33.30217139},
{"learn":[0.5250536462],"iteration":406,"passed_time":22.81036264,"remaining_time":33.23475441},
{"learn":[0.5241805933],"iteration":407,"passed_time":22.86768998,"remaining_time":33.18056978},
{"learn":[0.5236573314],"iteration":408,"passed_time":22.92256443,"remaining_time":33.12282537},
{"learn":[0.5230986302],"iteration":409,"passed_time":22.96911001,"remaining_time":33.05310952},
{"learn":[0.522840079],"iteration":410,"passed_time":23.01925483,"remaining_time":32.98866446},
{"learn":[0.5220771627],"iteration":411,"passed_time":23.06413081,"remaining_time":32.91676921},
{"learn":[0.5215568824],"iteration":412,"passed_time":23.11828533,"remaining_time":32.85819247},
{"learn":[0.5196806964],"iteration":413,"passed_time":23.17043507,"remaining_time":32.7967994},
{"learn":[0.5193921361],"iteration":414,"passed_time":23.21966275,"remaining_time":32.73133183},
{"learn":[0.519110228],"iteration":415,"passed_time":23.26490731,"remaining_time":32.66035065},
{"learn":[0.51836806],"iteration":416,"passed_time":23.31601125,"remaining_time":32.59768479},
{"learn":[0.517235667],"iteration":417,"passed_time":23.36442875,"remaining_time":32.53133381},
{"learn":[0.5163202213],"iteration":418,"passed_time":23.41688617,"remaining_time":32.47067032},
{"learn":[0.5154183637],"iteration":419,"passed_time":23.4617618,"remaining_time":32.39957582},
{"learn":[0.5148631223],"iteration":420,"passed_time":23.51396104,"remaining_time":32.33867801},
{"learn":[0.5144033208],"iteration":421,"passed_time":23.56959303,"remaining_time":32.28252316},
{"learn":[0.5127691133],"iteration":422,"passed_time":23.61781013,"remaining_time":32.21625637},
{"learn":[0.5119380247],"iteration":423,"passed_time":23.66879359,"remaining_time":32.1538328},
{"learn":[0.5101407064],"iteration":424,"passed_time":23.72582466,"remaining_time":32.09964513},
{"learn":[0.5090395079],"iteration":425,"passed_time":23.77505771,"remaining_time":32.03493691},
{"learn":[0.5087363307],"iteration":426,"passed_time":23.82483281,"remaining_time":31.97102857},
{"learn":[0.5079608372],"iteration":427,"passed_time":23.87261194,"remaining_time":31.90451876},
{"learn":[0.5071971679],"iteration":428,"passed_time":23.92119209,"remaining_time":31.83916243},
{"learn":[0.5064919528],"iteration":429,"passed_time":23.97265683,"remaining_time":31.7777079},
{"learn":[0.50545083],"iteration":430,"passed_time":24.02093888,"remaining_time":31.71209796},
{"learn":[0.5046812643],"iteration":431,"passed_time":24.07180314,"remaining_time":31.64996339},
{"learn":[0.5037192932],"iteration":432,"passed_time":24.12213928,"remaining_time":31.58718931},
{"learn":[0.5029907505],"iteration":433,"passed_time":24.17363261,"remaining_time":31.52598171},
{"learn":[0.5022273749],"iteration":434,"passed_time":24.23386748,"remaining_time":31.47617271},
{"learn":[0.5016552471],"iteration":435,"passed_time":24.28638366,"remaining_time":31.41633115},
{"learn":[0.5003291026],"iteration":436,"passed_time":24.33692712,"remaining_time":31.35398163},
{"learn":[0.50010134],"iteration":437,"passed_time":24.39447149,"remaining_time":31.30066889},
{"learn":[0.4994968802],"iteration":438,"passed_time":24.43709943,"remaining_time":31.22827512},
{"learn":[0.4988557688],"iteration":439,"passed_time":24.4906557,"remaining_time":31.16992544},
{"learn":[0.4983078711],"iteration":440,"passed_time":24.53884603,"remaining_time":31.10479576},
{"learn":[0.4976794818],"iteration":441,"passed_time":24.58835959,"remaining_time":31.04141324},
{"learn":[0.4968683344],"iteration":442,"passed_time":24.63754964,"remaining_time":30.97768657},
{"learn":[0.4949780107],"iteration":443,"passed_time":24.68932588,"remaining_time":30.91726394},
{"learn":[0.4934243078],"iteration":444,"passed_time":24.73629101,"remaining_time":30.8508798},
{"learn":[0.4928454896],"iteration":445,"passed_time":24.78409934,"remaining_time":30.78563012},
{"learn":[0.491231753],"iteration":446,"passed_time":24.83615023,"remaining_time":30.7257071},
{"learn":[0.4889337281],"iteration":447,"passed_time":24.88864251,"remaining_time":30.66636309},
{"learn":[0.4882892465],"iteration":448,"passed_time":24.93957224,"remaining_time":30.60513208},
{"learn":[0.4876803778],"iteration":449,"passed_time":24.98518424,"remaining_time":30.53744741},
{"learn":[0.4871737523],"iteration":450,"passed_time":25.03679475,"remaining_time":30.47716257},
{"learn":[0.4868299569],"iteration":451,"passed_time":25.08817099,"remaining_time":30.41663208},
{"learn":[0.4856354081],"iteration":452,"passed_time":25.1402561,"remaining_time":30.35699798},
{"learn":[0.4853989552],"iteration":453,"passed_time":25.18672459,"remaining_time":30.29064235},
{"learn":[0.4844468046],"iteration":454,"passed_time":25.23715994,"remaining_time":30.22912564},
{"learn":[0.4837339753],"iteration":455,"passed_time":25.28655873,"remaining_time":30.16642094},
{"learn":[0.4822029065],"iteration":456,"passed_time":25.33325427,"remaining_time":30.10056252},
{"learn":[0.4809157384],"iteration":457,"passed_time":25.3870302,"remaining_time":30.04316675},
{"learn":[0.4795901545],"iteration":458,"passed_time":25.44117591,"remaining_time":29.98622258},
{"learn":[0.4791650437],"iteration":459,"passed_time":25.49693431,"remaining_time":29.93118376},
{"learn":[0.4787859938],"iteration":460,"passed_time":25.55235951,"remaining_time":29.87575222},
{"learn":[0.4782866712],"iteration":461,"passed_time":25.60276116,"remaining_time":29.81447079},
{"learn":[0.4774260835],"iteration":462,"passed_time":25.65070633,"remaining_time":29.75038726},
{"learn":[0.4764716383],"iteration":463,"passed_time":25.70019532,"remaining_time":29.68815667},
{"learn":[0.476000046],"iteration":464,"passed_time":25.74870797,"remaining_time":29.62485755},
{"learn":[0.4754839184],"iteration":465,"passed_time":25.80298106,"remaining_time":29.56822294},
{"learn":[0.4743341849],"iteration":466,"passed_time":25.85103931,"remaining_time":29.50450525},
{"learn":[0.4732676801],"iteration":467,"passed_time":25.90194301,"remaining_time":29.44408906},
{"learn":[0.4717263582],"iteration":468,"passed_time":25.95001112,"remaining_time":29.38050299},
{"learn":[0.4708320036],"iteration":469,"passed_time":25.98986766,"remaining_time":29.30772311},
{"learn":[0.4684789149],"iteration":470,"passed_time":26.04428739,"remaining_time":29.25143955},
{"learn":[0.4678040607],"iteration":471,"passed_time":26.09134685,"remaining_time":29.18693038},
{"learn":[0.467350118],"iteration":472,"passed_time":26.1428288,"remaining_time":29.12742236},
{"learn":[0.4667572429],"iteration":473,"passed_time":26.19734516,"remaining_time":29.07131551},
{"learn":[0.4660113748],"iteration":474,"passed_time":26.24340252,"remaining_time":29.00586594},
{"learn":[0.4650806632],"iteration":475,"passed_time":26.29527174,"remaining_time":28.94689578},
{"learn":[0.4643252125],"iteration":476,"passed_time":26.34707507,"remaining_time":28.88788315},
{"learn":[0.463804097],"iteration":477,"passed_time":26.39477634,"remaining_time":28.82442103},
{"learn":[0.4633400631],"iteration":478,"passed_time":26.44843206,"remaining_time":28.76750126},
{"learn":[0.4627697105],"iteration":479,"passed_time":26.50861677,"remaining_time":28.71766817},
{"learn":[0.4622312071],"iteration":480,"passed_time":26.56023807,"remaining_time":28.65855209},
{"learn":[0.4616513701],"iteration":481,"passed_time":26.60533291,"remaining_time":28.59245321},
{"learn":[0.4608468113],"iteration":482,"passed_time":26.64935107,"remaining_time":28.52528883},
{"learn":[0.4592212005],"iteration":483,"passed_time":26.70611282,"remaining_time":28.47180623},
{"learn":[0.4582052728],"iteration":484,"passed_time":26.75461486,"remaining_time":28.40953949},
{"learn":[0.4567969584],"iteration":485,"passed_time":26.81132406,"remaining_time":28.35600939},
{"learn":[0.4560020392],"iteration":486,"passed_time":26.86302671,"remaining_time":28.29719241},
{"learn":[0.4555062176],"iteration":487,"passed_time":26.91234211,"remaining_time":28.23589992},
{"learn":[0.4544576382],"iteration":488,"passed_time":26.95846281,"remaining_time":28.17131798},
{"learn":[0.4538461063],"iteration":489,"passed_time":27.00996345,"remaining_time":28.11241094},
{"learn":[0.4527030391],"iteration":490,"passed_time":27.06068538,"remaining_time":28.0527268},
{"learn":[0.452048724],"iteration":491,"passed_time":27.11197813,"remaining_time":27.99366847},
{"learn":[0.4517768293],"iteration":492,"passed_time":27.16122817,"remaining_time":27.93254093},
{"learn":[0.451134561],"iteration":493,"passed_time":27.21324037,"remaining_time":27.87429074},
{"learn":[0.4507525241],"iteration":494,"passed_time":27.26097321,"remaining_time":27.81169994},
{"learn":[0.4500292282],"iteration":495,"passed_time":27.31970703,"remaining_time":27.76034747},
{"learn":[0.4484049389],"iteration":496,"passed_time":27.36563371,"remaining_time":27.69600354},
{"learn":[0.4474844625],"iteration":497,"passed_time":27.40983725,"remaining_time":27.62999659},
{"learn":[0.4472458792],"iteration":498,"passed_time":27.46710615,"remaining_time":27.57719475},
{"learn":[0.4469340159],"iteration":499,"passed_time":27.52002812,"remaining_time":27.52002812},
{"learn":[0.4466356797],"iteration":500,"passed_time":27.56881253,"remaining_time":27.45875739},
{"learn":[0.4449769879],"iteration":501,"passed_time":27.61860901,"remaining_time":27.39854042},
{"learn":[0.444701372],"iteration":502,"passed_time":27.6726346,"remaining_time":27.34254353},
{"learn":[0.4441340955],"iteration":503,"passed_time":27.72215451,"remaining_time":27.28212031},
{"learn":[0.4428135357],"iteration":504,"passed_time":27.80753363,"remaining_time":27.2568894},
{"learn":[0.4416445904],"iteration":505,"passed_time":27.90587709,"remaining_time":27.24407763},
{"learn":[0.4405729325],"iteration":506,"passed_time":27.95876871,"remaining_time":27.1867317},
{"learn":[0.4391706605],"iteration":507,"passed_time":28.00744187,"remaining_time":27.12531771},
{"learn":[0.4383627374],"iteration":508,"passed_time":28.06328538,"remaining_time":27.07087058},
{"learn":[0.4377851589],"iteration":509,"passed_time":28.1124752,"remaining_time":27.01002519},
{"learn":[0.4371184733],"iteration":510,"passed_time":28.16743322,"remaining_time":26.95474529},
{"learn":[0.4356909194],"iteration":511,"passed_time":28.21316111,"remaining_time":26.89066918},
{"learn":[0.4350218384],"iteration":512,"passed_time":28.26839418,"remaining_time":26.83568804},
{"learn":[0.4343331896],"iteration":513,"passed_time":28.41709249,"remaining_time":26.86907967},
{"learn":[0.4337628052],"iteration":514,"passed_time":28.47161259,"remaining_time":26.81307205},
{"learn":[0.4333112257],"iteration":515,"passed_time":28.52392896,"remaining_time":26.75500313},
{"learn":[0.4330607904],"iteration":516,"passed_time":28.57385874,"remaining_time":26.69472683},
{"learn":[0.4327152617],"iteration":517,"passed_time":28.62310361,"remaining_time":26.63385317},
{"learn":[0.4323794311],"iteration":518,"passed_time":28.67099906,"remaining_time":26.57177369},
{"learn":[0.4319151203],"iteration":519,"passed_time":28.72579169,"remaining_time":26.5161154},
{"learn":[0.430937626],"iteration":520,"passed_time":28.77413112,"remaining_time":26.45452746},
{"learn":[0.4302480793],"iteration":521,"passed_time":28.83005658,"remaining_time":26.39993687},
{"learn":[0.4285164737],"iteration":522,"passed_time":28.8797082,"remaining_time":26.33961914},
{"learn":[0.4282595718],"iteration":523,"passed_time":28.92643042,"remaining_time":26.27668107},
{"learn":[0.4278700311],"iteration":524,"passed_time":28.97899809,"remaining_time":26.21909351},
{"learn":[0.4275202351],"iteration":525,"passed_time":29.02348548,"remaining_time":26.15424357},
{"learn":[0.4268743578],"iteration":526,"passed_time":29.08497414,"remaining_time":26.10473011},
{"learn":[0.4261194452],"iteration":527,"passed_time":29.13913826,"remaining_time":26.0486236},
{"learn":[0.4247973216],"iteration":528,"passed_time":29.18020121,"remaining_time":25.98085968},
{"learn":[0.4244351541],"iteration":529,"passed_time":29.23296807,"remaining_time":25.92357546},
{"learn":[0.4240098283],"iteration":530,"passed_time":29.28973996,"remaining_time":25.86984565},
{"learn":[0.4234326812],"iteration":531,"passed_time":29.33846045,"remaining_time":25.80902159},
{"learn":[0.4225106218],"iteration":532,"passed_time":29.3949684,"remaining_time":25.75506612},
{"learn":[0.4213645599],"iteration":533,"passed_time":29.45714212,"remaining_time":25.70604537},
{"learn":[0.420781791],"iteration":534,"passed_time":29.50629753,"remaining_time":25.64566047},
{"learn":[0.4202077465],"iteration":535,"passed_time":29.55435519,"remaining_time":25.58436718},
{"learn":[0.4192628313],"iteration":536,"passed_time":29.6046983,"remaining_time":25.52509369},
{"learn":[0.4186315664],"iteration":537,"passed_time":29.65187665,"remaining_time":25.46313571},
{"learn":[0.4182059347],"iteration":538,"passed_time":29.70528173,"remaining_time":25.40655822},
{"learn":[0.4175132314],"iteration":539,"passed_time":29.75385301,"remaining_time":25.34587478},
{"learn":[0.41676317],"iteration":540,"passed_time":29.80439077,"remaining_time":25.28690456},
{"learn":[0.4165488484],"iteration":541,"passed_time":29.85301595,"remaining_time":25.22634927},
{"learn":[0.4160124008],"iteration":542,"passed_time":29.90085198,"remaining_time":25.16517377},
{"learn":[0.4153078664],"iteration":543,"passed_time":29.9510465,"remaining_time":25.10602428},
{"learn":[0.4142545077],"iteration":544,"passed_time":29.99687442,"remaining_time":25.04326213},
{"learn":[0.4135300684],"iteration":545,"passed_time":30.05073039,"remaining_time":24.98723736},
{"learn":[0.4131870058],"iteration":546,"passed_time":30.10101437,"remaining_time":24.92826236},
{"learn":[0.413011905],"iteration":547,"passed_time":30.15259149,"remaining_time":24.87038568},
{"learn":[0.4128187779],"iteration":548,"passed_time":30.19972554,"remaining_time":24.808882},
{"learn":[0.4119181107],"iteration":549,"passed_time":30.25602766,"remaining_time":24.75493172},
{"learn":[0.4109019238],"iteration":550,"passed_time":30.30308595,"remaining_time":24.69344028},
{"learn":[0.4104227936],"iteration":551,"passed_time":30.35586154,"remaining_time":24.63664125},
{"learn":[0.4099479517],"iteration":552,"passed_time":30.40349133,"remaining_time":24.57569734},
{"learn":[0.4092468549],"iteration":553,"passed_time":30.45197645,"remaining_time":24.51549006},
{"learn":[0.408699746],"iteration":554,"passed_time":30.50097566,"remaining_time":24.45573724},
{"learn":[0.4076398301],"iteration":555,"passed_time":30.54957695,"remaining_time":24.39570534},
{"learn":[0.4070687848],"iteration":556,"passed_time":30.60276576,"remaining_time":24.33936308},
{"learn":[0.4068073185],"iteration":557,"passed_time":30.6528907,"remaining_time":24.28060518},
{"learn":[0.4066065722],"iteration":558,"passed_time":30.70651976,"remaining_time":24.2246426},
{"learn":[0.4062194937],"iteration":559,"passed_time":30.76001664,"remaining_time":24.1685845},
{"learn":[0.4057443686],"iteration":560,"passed_time":30.80992703,"remaining_time":24.10972899},
{"learn":[0.4046510427],"iteration":561,"passed_time":30.85640863,"remaining_time":24.04823306},
{"learn":[0.4034269689],"iteration":562,"passed_time":30.90581176,"remaining_time":23.98905815},
{"learn":[0.4026997008],"iteration":563,"passed_time":30.95509195,"remaining_time":23.92982285},
{"learn":[0.4022165558],"iteration":564,"passed_time":31.00803956,"remaining_time":23.87344639},
{"learn":[0.4019306953],"iteration":565,"passed_time":31.05746444,"remaining_time":23.81438086},
{"learn":[0.401203869],"iteration":566,"passed_time":31.10574454,"remaining_time":23.75447511},
{"learn":[0.4008146946],"iteration":567,"passed_time":31.15410181,"remaining_time":23.69466898},
{"learn":[0.4005270963],"iteration":568,"passed_time":31.20552234,"remaining_time":23.63722342},
{"learn":[0.3998177196],"iteration":569,"passed_time":31.26241304,"remaining_time":23.58392563},
{"learn":[0.399646821],"iteration":570,"passed_time":31.31064601,"remaining_time":23.52411058},
{"learn":[0.3987822756],"iteration":571,"passed_time":31.36580091,"remaining_time":23.46951537},
{"learn":[0.3981884929],"iteration":572,"passed_time":31.42354451,"remaining_time":23.41684731},
{"learn":[0.3979144005],"iteration":573,"passed_time":31.47353695,"remaining_time":23.35840896},
{"learn":[0.397346575],"iteration":574,"passed_time":31.51983017,"remaining_time":23.29726578},
{"learn":[0.3968464738],"iteration":575,"passed_time":31.57060371,"remaining_time":23.23947218},
{"learn":[0.3962685372],"iteration":576,"passed_time":31.61565431,"remaining_time":23.17750741},
{"learn":[0.3958406284],"iteration":577,"passed_time":31.67572306,"remaining_time":23.12656597},
{"learn":[0.3946840788],"iteration":578,"passed_time":31.71793249,"remaining_time":23.06260722},
{"learn":[0.3942128342],"iteration":579,"passed_time":31.77217227,"remaining_time":23.00743509},
{"learn":[0.3939394884],"iteration":580,"passed_time":31.82163096,"remaining_time":22.94881819},
{"learn":[0.3935522807],"iteration":581,"passed_time":31.87110759,"remaining_time":22.89024566},
{"learn":[0.3932804128],"iteration":582,"passed_time":31.92176081,"remaining_time":22.8325459},
{"learn":[0.3924654568],"iteration":583,"passed_time":31.97068154,"remaining_time":22.77363616},
{"learn":[0.3917671344],"iteration":584,"passed_time":32.02703941,"remaining_time":22.7200365},
{"learn":[0.3913031259],"iteration":585,"passed_time":32.07880324,"remaining_time":22.66318181},
{"learn":[0.3910717293],"iteration":586,"passed_time":32.13044199,"remaining_time":22.60625646},
{"learn":[0.3905089734],"iteration":587,"passed_time":32.17983673,"remaining_time":22.54777676},
{"learn":[0.390136166],"iteration":588,"passed_time":32.23242815,"remaining_time":22.49155852},
{"learn":[0.3889373925],"iteration":589,"passed_time":32.27962509,"remaining_time":22.43160388},
{"learn":[0.3885902632],"iteration":590,"passed_time":32.33733795,"remaining_time":22.37896992},
{"learn":[0.3876369648],"iteration":591,"passed_time":32.38402126,"remaining_time":22.31871735},
{"learn":[0.3866301168],"iteration":592,"passed_time":32.43900109,"remaining_time":22.26420479},
{"learn":[0.3856515346],"iteration":593,"passed_time":32.48404027,"remaining_time":22.20289621},
{"learn":[0.3850957032],"iteration":594,"passed_time":32.53010209,"remaining_time":22.1423384},
{"learn":[0.3841214402],"iteration":595,"passed_time":32.58020394,"remaining_time":22.08456777},
{"learn":[0.3834382199],"iteration":596,"passed_time":32.62401981,"remaining_time":22.02257954},
{"learn":[0.3824871342],"iteration":597,"passed_time":32.6875877,"remaining_time":21.97393019},
{"learn":[0.3819515749],"iteration":598,"passed_time":32.74067795,"remaining_time":21.91821679},
{"learn":[0.3804134984],"iteration":599,"passed_time":32.79139932,"remaining_time":21.86093288},
{"learn":[0.3796554027],"iteration":600,"passed_time":32.83816273,"remaining_time":21.80104315},
{"learn":[0.3792195902],"iteration":601,"passed_time":32.88921462,"remaining_time":21.74403225},
{"learn":[0.3788284846],"iteration":602,"passed_time":32.93864929,"remaining_time":21.6859764},
{"learn":[0.3785327219],"iteration":603,"passed_time":32.99148094,"remaining_time":21.63017624},
{"learn":[0.3782006392],"iteration":604,"passed_time":33.03675921,"remaining_time":21.56945436},
{"learn":[0.3774875487],"iteration":605,"passed_time":33.09044109,"remaining_time":21.51424717},
{"learn":[0.3769640237],"iteration":606,"passed_time":33.13652254,"remaining_time":21.45412415},
{"learn":[0.3760945506],"iteration":607,"passed_time":33.1913736,"remaining_time":21.3997014},
{"learn":[0.3751904855],"iteration":608,"passed_time":33.23834677,"remaining_time":21.34021936},
{"learn":[0.3748582215],"iteration":609,"passed_time":33.28758026,"remaining_time":21.28222344},
{"learn":[0.3744220575],"iteration":610,"passed_time":33.34189307,"remaining_time":21.22749002},
{"learn":[0.3738079287],"iteration":611,"passed_time":33.39600852,"remaining_time":21.17263285},
{"learn":[0.37299452],"iteration":612,"passed_time":33.44490433,"remaining_time":21.11448283},
{"learn":[0.3725087503],"iteration":613,"passed_time":33.49401488,"remaining_time":21.05649796},
{"learn":[0.3718266846],"iteration":614,"passed_time":33.54064087,"remaining_time":20.99698656},
{"learn":[0.3714266518],"iteration":615,"passed_time":33.58933128,"remaining_time":20.93880391},
{"learn":[0.3708483541],"iteration":616,"passed_time":33.64070557,"remaining_time":20.88231805},
{"learn":[0.36981523],"iteration":617,"passed_time":33.69137675,"remaining_time":20.82541411},
{"learn":[0.3693268333],"iteration":618,"passed_time":33.74500521,"remaining_time":20.77035054},
{"learn":[0.3688826569],"iteration":619,"passed_time":33.79406131,"remaining_time":20.71248919},
{"learn":[0.3686438927],"iteration":620,"passed_time":33.84379492,"remaining_time":20.65506969},
{"learn":[0.3682279179],"iteration":621,"passed_time":33.89482469,"remaining_time":20.59846259},
{"learn":[0.3677299645],"iteration":622,"passed_time":33.94709497,"remaining_time":20.54262408},
{"learn":[0.3673853399],"iteration":623,"passed_time":33.99421722,"remaining_time":20.48369499},
{"learn":[0.3667861733],"iteration":624,"passed_time":34.04788482,"remaining_time":20.42873089},
{"learn":[0.3666511108],"iteration":625,"passed_time":34.10062326,"remaining_time":20.37321581},
{"learn":[0.3663564737],"iteration":626,"passed_time":34.15075474,"remaining_time":20.31615872},
{"learn":[0.3651781297],"iteration":627,"passed_time":34.20276488,"remaining_time":20.26023652},
{"learn":[0.3648813408],"iteration":628,"passed_time":34.24719368,"remaining_time":20.1998551},
{"learn":[0.3645923582],"iteration":629,"passed_time":34.30338546,"remaining_time":20.14643273},
{"learn":[0.3639761966],"iteration":630,"passed_time":34.35130639,"remaining_time":20.08816491},
{"learn":[0.3635515013],"iteration":631,"passed_time":34.4025589,"remaining_time":20.03186974},
{"learn":[0.3631567467],"iteration":632,"passed_time":34.45213508,"remaining_time":19.9746186},
{"learn":[0.3624738304],"iteration":633,"passed_time":34.50280656,"remaining_time":19.91802397},
{"learn":[0.3619905803],"iteration":634,"passed_time":34.5516683,"remaining_time":19.86040776},
{"learn":[0.3609236741],"iteration":635,"passed_time":34.60228374,"remaining_time":19.80382277},
{"learn":[0.3605567733],"iteration":636,"passed_time":34.6502055,"remaining_time":19.7457215},
{"learn":[0.3603084496],"iteration":637,"passed_time":34.70830137,"remaining_time":19.69342492},
{"learn":[0.3594445174],"iteration":638,"passed_time":34.75740058,"remaining_time":19.63602756},
{"learn":[0.3586088282],"iteration":639,"passed_time":34.80605572,"remaining_time":19.57840634},
{"learn":[0.3583149196],"iteration":640,"passed_time":34.8559711,"remaining_time":19.52151891},
{"learn":[0.3579673581],"iteration":641,"passed_time":34.90660988,"remaining_time":19.4650566},
{"learn":[0.3575615873],"iteration":642,"passed_time":34.95923725,"remaining_time":19.40971648},
{"learn":[0.3571545474],"iteration":643,"passed_time":35.00745184,"remaining_time":19.35194543},
{"learn":[0.3569249486],"iteration":644,"passed_time":35.06366304,"remaining_time":19.29860524},
{"learn":[0.3565952827],"iteration":645,"passed_time":35.11478878,"remaining_time":19.24246939},
{"learn":[0.3559448518],"iteration":646,"passed_time":35.20113923,"remaining_time":19.20556746},
{"learn":[0.3550203479],"iteration":647,"passed_time":35.28439809,"remaining_time":19.16683353},
{"learn":[0.3542398483],"iteration":648,"passed_time":35.37039654,"remaining_time":19.12944404},
{"learn":[0.3533304994],"iteration":649,"passed_time":35.55237837,"remaining_time":19.14358835},
{"learn":[0.3528166438],"iteration":650,"passed_time":35.67365133,"remaining_time":19.1245842},
{"learn":[0.3525662892],"iteration":651,"passed_time":35.72838058,"remaining_time":19.06974914},
{"learn":[0.352430558],"iteration":652,"passed_time":35.77831269,"remaining_time":19.01236524},
{"learn":[0.3522301274],"iteration":653,"passed_time":35.83020323,"remaining_time":18.95604024},
{"learn":[0.3515765849],"iteration":654,"passed_time":35.87953563,"remaining_time":18.89838136},
{"learn":[0.35115592],"iteration":655,"passed_time":35.92665026,"remaining_time":18.83958489},
{"learn":[0.3503991884],"iteration":656,"passed_time":35.97905156,"remaining_time":18.783584},
{"learn":[0.349294832],"iteration":657,"passed_time":36.02724704,"remaining_time":18.72540804},
{"learn":[0.3486080976],"iteration":658,"passed_time":36.08040399,"remaining_time":18.66982968},
{"learn":[0.3483451203],"iteration":659,"passed_time":36.13607866,"remaining_time":18.61555568},
{"learn":[0.3475043214],"iteration":660,"passed_time":36.19252653,"remaining_time":18.56167397},
{"learn":[0.3465704456],"iteration":661,"passed_time":36.24083093,"remaining_time":18.50362667},
{"learn":[0.3457515899],"iteration":662,"passed_time":36.29316852,"remaining_time":18.44765881},
{"learn":[0.3455543499],"iteration":663,"passed_time":36.34780746,"remaining_time":18.39286642},
{"learn":[0.3451707923],"iteration":664,"passed_time":36.4830782,"remaining_time":18.37869353},
{"learn":[0.3447502832],"iteration":665,"passed_time":36.55558814,"remaining_time":18.33268234},
{"learn":[0.3439754078],"iteration":666,"passed_time":36.60678786,"remaining_time":18.27595256},
{"learn":[0.3435623034],"iteration":667,"passed_time":36.66375014,"remaining_time":18.22210336},
{"learn":[0.3429643376],"iteration":668,"passed_time":36.71542764,"remaining_time":18.16563012},
{"learn":[0.3426014889],"iteration":669,"passed_time":36.77729736,"remaining_time":18.11419124},
{"learn":[0.3423035621],"iteration":670,"passed_time":36.82996748,"remaining_time":18.05821058},
{"learn":[0.3418278104],"iteration":671,"passed_time":36.88248095,"remaining_time":18.00216332},
{"learn":[0.3415744596],"iteration":672,"passed_time":36.92728546,"remaining_time":17.9423809},
{"learn":[0.3405906879],"iteration":673,"passed_time":36.98141747,"remaining_time":17.88715445},
{"learn":[0.3402962734],"iteration":674,"passed_time":37.03041531,"remaining_time":17.82945922},
{"learn":[0.3400206345],"iteration":675,"passed_time":37.08299423,"remaining_time":17.77350611},
{"learn":[0.3397010943],"iteration":676,"passed_time":37.1362435,"remaining_time":17.71788279},
{"learn":[0.3386953929],"iteration":677,"passed_time":37.19886194,"remaining_time":17.66671614},
{"learn":[0.3382484181],"iteration":678,"passed_time":37.25865491,"remaining_time":17.61418001},
{"learn":[0.3378060416],"iteration":679,"passed_time":37.31024769,"remaining_time":17.55776362},
{"learn":[0.3373603876],"iteration":680,"passed_time":37.36887443,"remaining_time":17.50465631},
{"learn":[0.3371551767],"iteration":681,"passed_time":37.4221787,"remaining_time":17.44905106},
{"learn":[0.3363543004],"iteration":682,"passed_time":37.47345206,"remaining_time":17.39250996},
{"learn":[0.3360652494],"iteration":683,"passed_time":37.52846626,"remaining_time":17.33771248},
{"learn":[0.3358547093],"iteration":684,"passed_time":37.58867705,"remaining_time":17.28530404},
{"learn":[0.3352832858],"iteration":685,"passed_time":37.64663005,"remaining_time":17.23183941},
{"learn":[0.3347361474],"iteration":686,"passed_time":37.70558238,"remaining_time":17.17881701},
{"learn":[0.3341876011],"iteration":687,"passed_time":37.76312249,"remaining_time":17.12513694},
{"learn":[0.3338694768],"iteration":688,"passed_time":37.82744577,"remaining_time":17.07450745},
{"learn":[0.333485842],"iteration":689,"passed_time":37.88032122,"remaining_time":17.01869504},
{"learn":[0.3328141389],"iteration":690,"passed_time":37.94042108,"remaining_time":16.96612173},
{"learn":[0.3325905224],"iteration":691,"passed_time":37.99852973,"remaining_time":16.9126404},
{"learn":[0.3323174364],"iteration":692,"passed_time":38.05358617,"remaining_time":16.85779359},
{"learn":[0.3320314712],"iteration":693,"passed_time":38.10588261,"remaining_time":16.80172922},
{"learn":[0.3316965959],"iteration":694,"passed_time":38.16662598,"remaining_time":16.74938262},
{"learn":[0.3311903356],"iteration":695,"passed_time":38.21830126,"remaining_time":16.69305113},
{"learn":[0.3307692678],"iteration":696,"passed_time":38.27501571,"remaining_time":16.63892361},
{"learn":[0.3304302316],"iteration":697,"passed_time":38.32973893,"remaining_time":16.58392716},
{"learn":[0.3300046412],"iteration":698,"passed_time":38.38510458,"remaining_time":16.52920812},
{"learn":[0.3296792728],"iteration":699,"passed_time":38.43904168,"remaining_time":16.473875},
{"learn":[0.3294187275],"iteration":700,"passed_time":38.49359915,"remaining_time":16.41881048},
{"learn":[0.3288683586],"iteration":701,"passed_time":38.54662489,"remaining_time":16.36309718},
{"learn":[0.3283620944],"iteration":702,"passed_time":38.6097405,"remaining_time":16.31165424},
{"learn":[0.3270376319],"iteration":703,"passed_time":38.75915483,"remaining_time":16.29646283},
{"learn":[0.3265912622],"iteration":704,"passed_time":38.81223065,"remaining_time":16.24057878},
{"learn":[0.3259557773],"iteration":705,"passed_time":38.86577269,"remaining_time":16.18489684},
{"learn":[0.3256748936],"iteration":706,"passed_time":38.92025646,"remaining_time":16.12961123},
{"learn":[0.3252249464],"iteration":707,"passed_time":38.97689297,"remaining_time":16.07521574},
{"learn":[0.3246827558],"iteration":708,"passed_time":39.03302109,"remaining_time":16.02060527},
{"learn":[0.3239649978],"iteration":709,"passed_time":39.08556758,"remaining_time":15.9645276},
{"learn":[0.3236824468],"iteration":710,"passed_time":39.13994754,"remaining_time":15.90920512},
{"learn":[0.3226252399],"iteration":711,"passed_time":39.19587757,"remaining_time":15.85451228},
{"learn":[0.3220123182],"iteration":712,"passed_time":39.26058607,"remaining_time":15.80334951},
{"learn":[0.3212697776],"iteration":713,"passed_time":39.323499,"remaining_time":15.75142957},
{"learn":[0.3210777404],"iteration":714,"passed_time":39.37430072,"remaining_time":15.69465134},
{"learn":[0.3207443738],"iteration":715,"passed_time":39.42570653,"remaining_time":15.6381294},
{"learn":[0.3203104142],"iteration":716,"passed_time":39.48587375,"remaining_time":15.58507987},
{"learn":[0.3199763533],"iteration":717,"passed_time":39.54336021,"remaining_time":15.53095763},
{"learn":[0.3196970522],"iteration":718,"passed_time":39.59719731,"remaining_time":15.47539978},
{"learn":[0.3191989396],"iteration":719,"passed_time":39.65699224,"remaining_time":15.42216365},
{"learn":[0.3188844001],"iteration":720,"passed_time":39.70963817,"remaining_time":15.36614293},
{"learn":[0.3186270825],"iteration":721,"passed_time":39.76915378,"remaining_time":15.31277666},
{"learn":[0.3180533761],"iteration":722,"passed_time":39.82265474,"remaining_time":15.25708902},
{"learn":[0.3178024281],"iteration":723,"passed_time":39.94072886,"remaining_time":15.22602371},
{"learn":[0.3176853171],"iteration":724,"passed_time":40.03219315,"remaining_time":15.18462499},
{"learn":[0.3173472699],"iteration":725,"passed_time":40.08773822,"remaining_time":15.12953205},
{"learn":[0.3170937159],"iteration":726,"passed_time":40.14259393,"remaining_time":15.07417901},
{"learn":[0.3168613284],"iteration":727,"passed_time":40.19538648,"remaining_time":15.01805649},
{"learn":[0.3164963309],"iteration":728,"passed_time":40.24858612,"remaining_time":14.96209443},
{"learn":[0.3162935369],"iteration":729,"passed_time":40.31494607,"remaining_time":14.91100745},
{"learn":[0.3160360945],"iteration":730,"passed_time":40.38823492,"remaining_time":14.86242845},
{"learn":[0.3156428276],"iteration":731,"passed_time":40.44367062,"remaining_time":14.80724553},
{"learn":[0.3151759113],"iteration":732,"passed_time":40.49896934,"remaining_time":14.75201202},
{"learn":[0.3146196225],"iteration":733,"passed_time":40.55149789,"remaining_time":14.69577444},
{"learn":[0.3141795825],"iteration":734,"passed_time":40.60469103,"remaining_time":14.63978656},
{"learn":[0.3139725162],"iteration":735,"passed_time":40.6601784,"remaining_time":14.58462921},
{"learn":[0.3137298752],"iteration":736,"passed_time":40.71120646,"remaining_time":14.52787965},
{"learn":[0.3135233194],"iteration":737,"passed_time":40.76270919,"remaining_time":14.4713141},
{"learn":[0.3130047558],"iteration":738,"passed_time":40.81315826,"remaining_time":14.41439013},
{"learn":[0.3126673494],"iteration":739,"passed_time":40.86237317,"remaining_time":14.35705003},
{"learn":[0.3124968703],"iteration":740,"passed_time":40.91613374,"remaining_time":14.3013207},
{"learn":[0.3122630774],"iteration":741,"passed_time":40.97177819,"remaining_time":14.24625171},
{"learn":[0.3116833415],"iteration":742,"passed_time":41.02573964,"remaining_time":14.19059904},
{"learn":[0.3111342815],"iteration":743,"passed_time":41.07666334,"remaining_time":14.13390567},
{"learn":[0.3109418392],"iteration":744,"passed_time":41.12532886,"remaining_time":14.07645484},
{"learn":[0.3101836192],"iteration":745,"passed_time":41.17978365,"remaining_time":14.02099872},
{"learn":[0.3099549834],"iteration":746,"passed_time":41.23519651,"remaining_time":13.96586977},
{"learn":[0.3097256469],"iteration":747,"passed_time":41.28630789,"remaining_time":13.90929089},
{"learn":[0.3092782397],"iteration":748,"passed_time":41.35031034,"remaining_time":13.85704659},
{"learn":[0.3089877324],"iteration":749,"passed_time":41.41075902,"remaining_time":13.80358634},
{"learn":[0.3083861391],"iteration":750,"passed_time":41.46786423,"remaining_time":13.74899893},
{"learn":[0.3080237674],"iteration":751,"passed_time":41.51957582,"remaining_time":13.69262607},
{"learn":[0.3076743497],"iteration":752,"passed_time":41.57600057,"remaining_time":13.63781161},
{"learn":[0.3071532341],"iteration":753,"passed_time":41.62966799,"remaining_time":13.58209327},
{"learn":[0.3068996832],"iteration":754,"passed_time":41.68337914,"remaining_time":13.52639456},
{"learn":[0.3067708416],"iteration":755,"passed_time":41.73724281,"remaining_time":13.47075032},
{"learn":[0.306463512],"iteration":756,"passed_time":41.79444701,"remaining_time":13.41618312},
{"learn":[0.3059613387],"iteration":757,"passed_time":41.84864121,"remaining_time":13.36064799},
{"learn":[0.3055329913],"iteration":758,"passed_time":41.90627454,"remaining_time":13.30620839},
{"learn":[0.3050179079],"iteration":759,"passed_time":41.96294148,"remaining_time":13.25145521},
{"learn":[0.304663279],"iteration":760,"passed_time":42.01862749,"remaining_time":13.19638892},
{"learn":[0.3039227841],"iteration":761,"passed_time":42.07340853,"remaining_time":13.14103836},
{"learn":[0.3034720797],"iteration":762,"passed_time":42.12989276,"remaining_time":13.08621833},
{"learn":[0.3032999762],"iteration":763,"passed_time":42.18296788,"remaining_time":13.03034086},
{"learn":[0.3027547291],"iteration":764,"passed_time":42.23984662,"remaining_time":12.97563916},
{"learn":[0.3023218835],"iteration":765,"passed_time":42.30353459,"remaining_time":12.92301187},
{"learn":[0.3020347919],"iteration":766,"passed_time":42.35919019,"remaining_time":12.86791567},
{"learn":[0.3019076371],"iteration":767,"passed_time":42.41743215,"remaining_time":12.81359929},
{"learn":[0.3013611176],"iteration":768,"passed_time":42.47089281,"remaining_time":12.75783646},
{"learn":[0.3011958889],"iteration":769,"passed_time":42.52378263,"remaining_time":12.7019091},
{"learn":[0.3007376578],"iteration":770,"passed_time":42.57751723,"remaining_time":12.64624053},
{"learn":[0.3005433312],"iteration":771,"passed_time":42.6323521,"remaining_time":12.59090191},
{"learn":[0.3000382061],"iteration":772,"passed_time":42.68531736,"remaining_time":12.53501558},
{"learn":[0.2998630552],"iteration":773,"passed_time":42.73669417,"remaining_time":12.47867298},
{"learn":[0.2997331754],"iteration":774,"passed_time":42.79816442,"remaining_time":12.42527354},
{"learn":[0.299085051],"iteration":775,"passed_time":42.84875691,"remaining_time":12.36871333},
{"learn":[0.2989368674],"iteration":776,"passed_time":42.89729528,"remaining_time":12.31157895},
{"learn":[0.2986361435],"iteration":777,"passed_time":42.9497745,"remaining_time":12.25559118},
{"learn":[0.2980066438],"iteration":778,"passed_time":42.99928202,"remaining_time":12.19876935},
{"learn":[0.2977838409],"iteration":779,"passed_time":43.05023456,"remaining_time":12.14237385},
{"learn":[0.2971170495],"iteration":780,"passed_time":43.10566008,"remaining_time":12.08724655},
{"learn":[0.2968208453],"iteration":781,"passed_time":43.15554286,"remaining_time":12.03057333},
{"learn":[0.296419178],"iteration":782,"passed_time":43.20794361,"remaining_time":11.97461528},
{"learn":[0.2960011483],"iteration":783,"passed_time":43.26369127,"remaining_time":11.91958841},
{"learn":[0.2955166919],"iteration":784,"passed_time":43.315964,"remaining_time":11.86360797},
{"learn":[0.295090373],"iteration":785,"passed_time":43.36404141,"remaining_time":11.80649474},
{"learn":[0.2947522629],"iteration":786,"passed_time":43.41662768,"remaining_time":11.75062477},
{"learn":[0.2946384727],"iteration":787,"passed_time":43.46776462,"remaining_time":11.69437322},
{"learn":[0.2942467846],"iteration":788,"passed_time":43.52016555,"remaining_time":11.63847266},
{"learn":[0.2937753767],"iteration":789,"passed_time":43.57129545,"remaining_time":11.58224309},
{"learn":[0.2931603425],"iteration":790,"passed_time":43.62272719,"remaining_time":11.52610617},
{"learn":[0.2930388845],"iteration":791,"passed_time":43.67464304,"remaining_time":11.47010827},
{"learn":[0.2926962933],"iteration":792,"passed_time":43.72577059,"remaining_time":11.4139149},
{"learn":[0.2924018028],"iteration":793,"passed_time":43.77425237,"remaining_time":11.35704785},
{"learn":[0.2918144694],"iteration":794,"passed_time":43.82722192,"remaining_time":11.30135911},
{"learn":[0.2914576054],"iteration":795,"passed_time":43.87668612,"remaining_time":11.24477886},
{"learn":[0.2908061417],"iteration":796,"passed_time":43.92890351,"remaining_time":11.18891771},
{"learn":[0.2901453583],"iteration":797,"passed_time":43.98009877,"remaining_time":11.13280696},
{"learn":[0.289997699],"iteration":798,"passed_time":44.02964336,"remaining_time":11.07629326},
{"learn":[0.2897255422],"iteration":799,"passed_time":44.08563531,"remaining_time":11.02140883},
{"learn":[0.2893418854],"iteration":800,"passed_time":44.13600957,"remaining_time":10.96512597},
{"learn":[0.2890807864],"iteration":801,"passed_time":44.18857427,"remaining_time":10.90939863},
{"learn":[0.2882707649],"iteration":802,"passed_time":44.24150665,"remaining_time":10.85376938},
{"learn":[0.287898561],"iteration":803,"passed_time":44.30069722,"remaining_time":10.79967246},
{"learn":[0.2876278236],"iteration":804,"passed_time":44.351696,"remaining_time":10.74357853},
{"learn":[0.2869935853],"iteration":805,"passed_time":44.40175605,"remaining_time":10.68727131},
{"learn":[0.2868455543],"iteration":806,"passed_time":44.45368694,"remaining_time":10.63142699},
{"learn":[0.2859045291],"iteration":807,"passed_time":44.50737361,"remaining_time":10.57600957},
{"learn":[0.2854549008],"iteration":808,"passed_time":44.55912792,"remaining_time":10.52014021},
{"learn":[0.2849997256],"iteration":809,"passed_time":44.62408204,"remaining_time":10.46737727},
{"learn":[0.2847920495],"iteration":810,"passed_time":44.6826372,"remaining_time":10.41309301},
{"learn":[0.2844501041],"iteration":811,"passed_time":44.73485376,"remaining_time":10.35733067},
{"learn":[0.2841912142],"iteration":812,"passed_time":44.78820034,"remaining_time":10.30183698},
{"learn":[0.2838379107],"iteration":813,"passed_time":44.84495452,"remaining_time":10.2471272},
{"learn":[0.2836666463],"iteration":814,"passed_time":44.89805062,"remaining_time":10.19158204},
{"learn":[0.2831399069],"iteration":815,"passed_time":44.95711296,"remaining_time":10.13738822},
{"learn":[0.28298952],"iteration":816,"passed_time":45.01389902,"remaining_time":10.08267261},
{"learn":[0.2827069895],"iteration":817,"passed_time":45.07019893,"remaining_time":10.02784377},
{"learn":[0.2821559186],"iteration":818,"passed_time":45.12493743,"remaining_time":9.97266627},
{"learn":[0.2818304903],"iteration":819,"passed_time":45.17730645,"remaining_time":9.916969708},
{"learn":[0.2817071225],"iteration":820,"passed_time":45.23336416,"remaining_time":9.862085486},
{"learn":[0.2816048627],"iteration":821,"passed_time":45.28698922,"remaining_time":9.806671631},
{"learn":[0.2812574233],"iteration":822,"passed_time":45.34219128,"remaining_time":9.751601284},
{"learn":[0.2811596891],"iteration":823,"passed_time":45.39311484,"remaining_time":9.695616762},
{"learn":[0.2808684607],"iteration":824,"passed_time":45.44162692,"remaining_time":9.639132984},
{"learn":[0.28071396],"iteration":825,"passed_time":45.49980638,"remaining_time":9.584704975},
{"learn":[0.2805418787],"iteration":826,"passed_time":45.5516869,"remaining_time":9.528950223},
{"learn":[0.2803005005],"iteration":827,"passed_time":45.60308586,"remaining_time":9.473104792},
{"learn":[0.2797785932],"iteration":828,"passed_time":45.65996587,"remaining_time":9.418400679},
{"learn":[0.2796350102],"iteration":829,"passed_time":45.70512272,"remaining_time":9.361290195},
{"learn":[0.2793951364],"iteration":830,"passed_time":45.75922863,"remaining_time":9.306028445},
{"learn":[0.279286949],"iteration":831,"passed_time":45.8131833,"remaining_time":9.250738936},
{"learn":[0.2789050308],"iteration":832,"passed_time":45.86597271,"remaining_time":9.195219018},
{"learn":[0.2786289672],"iteration":833,"passed_time":45.92957462,"remaining_time":9.141857779},
{"learn":[0.2785113471],"iteration":834,"passed_time":45.97869231,"remaining_time":9.085609857},
{"learn":[0.277913966],"iteration":835,"passed_time":46.03086843,"remaining_time":9.029978975},
{"learn":[0.2777544653],"iteration":836,"passed_time":46.10028549,"remaining_time":8.977713901},
{"learn":[0.2775440234],"iteration":837,"passed_time":46.15347647,"remaining_time":8.922271108},
{"learn":[0.2772907599],"iteration":838,"passed_time":46.20855871,"remaining_time":8.867196605},
{"learn":[0.2768770812],"iteration":839,"passed_time":46.26294862,"remaining_time":8.811990214},
{"learn":[0.2766322041],"iteration":840,"passed_time":46.31814917,"remaining_time":8.756939023},
{"learn":[0.2760823204],"iteration":841,"passed_time":46.37202873,"remaining_time":8.701639596},
{"learn":[0.2758135918],"iteration":842,"passed_time":46.42380604,"remaining_time":8.645952014},
{"learn":[0.2757173916],"iteration":843,"passed_time":46.47931001,"remaining_time":8.590962514},
{"learn":[0.2753705128],"iteration":844,"passed_time":46.53458479,"remaining_time":8.535929754},
{"learn":[0.2751966541],"iteration":845,"passed_time":46.58380282,"remaining_time":8.479793893},
{"learn":[0.2750998159],"iteration":846,"passed_time":46.63536657,"remaining_time":8.424098093},
{"learn":[0.274802602],"iteration":847,"passed_time":46.68984334,"remaining_time":8.368934184},
{"learn":[0.2746234816],"iteration":848,"passed_time":46.74029833,"remaining_time":8.313056593},
{"learn":[0.2743100839],"iteration":849,"passed_time":46.79586272,"remaining_time":8.258093421},
{"learn":[0.2742209438],"iteration":850,"passed_time":46.84696334,"remaining_time":8.202347282},
{"learn":[0.2737762751],"iteration":851,"passed_time":46.90329798,"remaining_time":8.147521245},
{"learn":[0.2734961096],"iteration":852,"passed_time":46.94949222,"remaining_time":8.090944146},
{"learn":[0.2726747585],"iteration":853,"passed_time":47.01196334,"remaining_time":8.03717406},
{"learn":[0.2724696827],"iteration":854,"passed_time":47.06538845,"remaining_time":7.981849503},
{"learn":[0.2723183275],"iteration":855,"passed_time":47.12170078,"remaining_time":7.927015084},
{"learn":[0.2721719257],"iteration":856,"passed_time":47.16886782,"remaining_time":7.870651223},
{"learn":[0.2717233995],"iteration":857,"passed_time":47.23830311,"remaining_time":7.817994221},
{"learn":[0.2711098213],"iteration":858,"passed_time":47.28761809,"remaining_time":7.761995518},
{"learn":[0.2706101517],"iteration":859,"passed_time":47.33609977,"remaining_time":7.705876707},
{"learn":[0.2704095835],"iteration":860,"passed_time":47.38570328,"remaining_time":7.649956743},
{"learn":[0.2700251406],"iteration":861,"passed_time":47.44127136,"remaining_time":7.59500632},
{"learn":[0.2697091337],"iteration":862,"passed_time":47.49205941,"remaining_time":7.539295643},
{"learn":[0.2694492032],"iteration":863,"passed_time":47.55088408,"remaining_time":7.484861384},
{"learn":[0.2692147835],"iteration":864,"passed_time":47.6047458,"remaining_time":7.429642407},
{"learn":[0.269090126],"iteration":865,"passed_time":47.65672306,"remaining_time":7.374134976},
{"learn":[0.2684252397],"iteration":866,"passed_time":47.70865695,"remaining_time":7.318629035},
{"learn":[0.2683308116],"iteration":867,"passed_time":47.7597791,"remaining_time":7.263007881},
{"learn":[0.2680428224],"iteration":868,"passed_time":47.81355713,"remaining_time":7.207797451},
{"learn":[0.2679354704],"iteration":869,"passed_time":47.87204426,"remaining_time":7.15329397},
{"learn":[0.2677935427],"iteration":870,"passed_time":47.9262639,"remaining_time":7.098149303},
{"learn":[0.267594488],"iteration":871,"passed_time":47.97596359,"remaining_time":7.04234328},
{"learn":[0.267373284],"iteration":872,"passed_time":48.02896156,"remaining_time":6.987031063},
{"learn":[0.2671813062],"iteration":873,"passed_time":48.08823903,"remaining_time":6.932629425},
{"learn":[0.26701512],"iteration":874,"passed_time":48.1390467,"remaining_time":6.877006672},
{"learn":[0.2666952334],"iteration":875,"passed_time":48.19198553,"remaining_time":6.821696582},
{"learn":[0.266517388],"iteration":876,"passed_time":48.24331454,"remaining_time":6.766166121},
{"learn":[0.2657750849],"iteration":877,"passed_time":48.29124491,"remaining_time":6.710172983},
{"learn":[0.2656724429],"iteration":878,"passed_time":48.34307909,"remaining_time":6.654735574},
{"learn":[0.2650838796],"iteration":879,"passed_time":48.39649302,"remaining_time":6.599521775},
{"learn":[0.2649546291],"iteration":880,"passed_time":48.44888324,"remaining_time":6.544173786},
{"learn":[0.2647974511],"iteration":881,"passed_time":48.50300308,"remaining_time":6.489063904},
{"learn":[0.2645371552],"iteration":882,"passed_time":48.55386983,"remaining_time":6.433525221},
{"learn":[0.2643586343],"iteration":883,"passed_time":48.60485672,"remaining_time":6.378012872},
{"learn":[0.2641951859],"iteration":884,"passed_time":48.65893239,"remaining_time":6.322912119},
{"learn":[0.2641291269],"iteration":885,"passed_time":48.70767463,"remaining_time":6.267127435},
{"learn":[0.2639547321],"iteration":886,"passed_time":48.76406452,"remaining_time":6.21233291},
{"learn":[0.2636226534],"iteration":887,"passed_time":48.81635124,"remaining_time":6.157017274},
{"learn":[0.2632216949],"iteration":888,"passed_time":48.87104295,"remaining_time":6.102008738},
{"learn":[0.2630621784],"iteration":889,"passed_time":48.92527993,"remaining_time":6.04694471},
{"learn":[0.2627400207],"iteration":890,"passed_time":48.97850986,"remaining_time":5.991759343},
{"learn":[0.2625166519],"iteration":891,"passed_time":49.02860148,"remaining_time":5.936198385},
{"learn":[0.2618150581],"iteration":892,"passed_time":49.08441154,"remaining_time":5.881334865},
{"learn":[0.2614191624],"iteration":893,"passed_time":49.13668538,"remaining_time":5.826049945},
{"learn":[0.2611014672],"iteration":894,"passed_time":49.19201814,"remaining_time":5.771130619},
{"learn":[0.2606267178],"iteration":895,"passed_time":49.24284768,"remaining_time":5.715687677},
{"learn":[0.2604665714],"iteration":896,"passed_time":49.29414957,"remaining_time":5.660309259},
{"learn":[0.2603404975],"iteration":897,"passed_time":49.34634616,"remaining_time":5.605041546},
{"learn":[0.2601911212],"iteration":898,"passed_time":49.39758808,"remaining_time":5.54967341},
{"learn":[0.2599769143],"iteration":899,"passed_time":49.45122102,"remaining_time":5.494580114},
{"learn":[0.2597000084],"iteration":900,"passed_time":49.49985708,"remaining_time":5.438941011},
{"learn":[0.2593708366],"iteration":901,"passed_time":49.55312587,"remaining_time":5.38382077},
{"learn":[0.2591569199],"iteration":902,"passed_time":49.60725052,"remaining_time":5.328796568},
{"learn":[0.2590767106],"iteration":903,"passed_time":49.66001009,"remaining_time":5.27362939},
{"learn":[0.2589510314],"iteration":904,"passed_time":49.71477719,"remaining_time":5.218678268},
{"learn":[0.2587324879],"iteration":905,"passed_time":49.76642119,"remaining_time":5.163403524},
{"learn":[0.2583729178],"iteration":906,"passed_time":49.82131536,"remaining_time":5.108470042},
{"learn":[0.2581722963],"iteration":907,"passed_time":49.87830834,"remaining_time":5.053749304},
{"learn":[0.2575832725],"iteration":908,"passed_time":49.9323716,"remaining_time":4.99873027},
{"learn":[0.2574177174],"iteration":909,"passed_time":49.98727412,"remaining_time":4.943796341},
{"learn":[0.2571604366],"iteration":910,"passed_time":50.0429676,"remaining_time":4.888939755},
{"learn":[0.2570080512],"iteration":911,"passed_time":50.0950349,"remaining_time":4.833731438},
{"learn":[0.2565644545],"iteration":912,"passed_time":50.15268365,"remaining_time":4.779061859},
{"learn":[0.2563192966],"iteration":913,"passed_time":50.20846389,"remaining_time":4.72420995},
{"learn":[0.2559280872],"iteration":914,"passed_time":50.26333097,"remaining_time":4.669271183},
{"learn":[0.2556902308],"iteration":915,"passed_time":50.32356423,"remaining_time":4.614824668},
{"learn":[0.2555965935],"iteration":916,"passed_time":50.38347444,"remaining_time":4.560336291},
{"learn":[0.2553961128],"iteration":917,"passed_time":50.43787508,"remaining_time":4.505343961},
{"learn":[0.2552702454],"iteration":918,"passed_time":50.49555043,"remaining_time":4.45064155},
{"learn":[0.2551837362],"iteration":919,"passed_time":50.54481819,"remaining_time":4.395201582},
{"learn":[0.2550796426],"iteration":920,"passed_time":50.59998448,"remaining_time":4.340280971},
{"learn":[0.2548361019],"iteration":921,"passed_time":50.64433127,"remaining_time":4.284444511},
{"learn":[0.2544900238],"iteration":922,"passed_time":50.69930385,"remaining_time":4.22951939},
{"learn":[0.2541821715],"iteration":923,"passed_time":50.75559568,"remaining_time":4.174702675},
{"learn":[0.2541117506],"iteration":924,"passed_time":50.80988686,"remaining_time":4.119720556},
{"learn":[0.2539431722],"iteration":925,"passed_time":50.86572465,"remaining_time":4.064863525},
{"learn":[0.2536594534],"iteration":926,"passed_time":50.98349612,"remaining_time":4.014881571},
{"learn":[0.2531216392],"iteration":927,"passed_time":51.13164847,"remaining_time":3.967110657},
{"learn":[0.2527091434],"iteration":928,"passed_time":51.26570548,"remaining_time":3.918046382},
{"learn":[0.2521977135],"iteration":929,"passed_time":51.42548428,"remaining_time":3.870735376},
{"learn":[0.2520705481],"iteration":930,"passed_time":51.50144937,"remaining_time":3.816971006},
{"learn":[0.2517526614],"iteration":931,"passed_time":51.56756593,"remaining_time":3.762440433},
{"learn":[0.2516073771],"iteration":932,"passed_time":51.65812377,"remaining_time":3.709640185},
{"learn":[0.2512834696],"iteration":933,"passed_time":51.7572011,"remaining_time":3.657361106},
{"learn":[0.2511020087],"iteration":934,"passed_time":51.81580255,"remaining_time":3.602168092},
{"learn":[0.2508664362],"iteration":935,"passed_time":51.86371194,"remaining_time":3.546236714},
{"learn":[0.2507986075],"iteration":936,"passed_time":51.91280851,"remaining_time":3.49040228},
{"learn":[0.2505704059],"iteration":937,"passed_time":51.95930694,"remaining_time":3.43441048},
{"learn":[0.2505124445],"iteration":938,"passed_time":52.01391709,"remaining_time":3.37896586},
{"learn":[0.2502221798],"iteration":939,"passed_time":52.09847833,"remaining_time":3.325434787},
{"learn":[0.2499531923],"iteration":940,"passed_time":52.24704559,"remaining_time":3.275850892},
{"learn":[0.2496439348],"iteration":941,"passed_time":52.36466687,"remaining_time":3.224151463},
{"learn":[0.2495813156],"iteration":942,"passed_time":52.48711371,"remaining_time":3.172603904},
{"learn":[0.2488958957],"iteration":943,"passed_time":52.54941852,"remaining_time":3.117338387},
{"learn":[0.2484858626],"iteration":944,"passed_time":52.64177533,"remaining_time":3.06380703},
{"learn":[0.2482309186],"iteration":945,"passed_time":52.73410305,"remaining_time":3.010191929},
{"learn":[0.2480364977],"iteration":946,"passed_time":52.83385343,"remaining_time":2.956910488},
{"learn":[0.2478632787],"iteration":947,"passed_time":52.88763227,"remaining_time":2.901009365},
{"learn":[0.2477296179],"iteration":948,"passed_time":52.93786889,"remaining_time":2.844922353},
{"learn":[0.2471557404],"iteration":949,"passed_time":52.99788368,"remaining_time":2.789362299},
{"learn":[0.2470782322],"iteration":950,"passed_time":53.0486364,"remaining_time":2.73331565},
{"learn":[0.2469246288],"iteration":951,"passed_time":53.10571302,"remaining_time":2.677598976},
{"learn":[0.246702214],"iteration":952,"passed_time":53.16070469,"remaining_time":2.621776622},
{"learn":[0.2466075075],"iteration":953,"passed_time":53.21951995,"remaining_time":2.566140375},
{"learn":[0.2464293317],"iteration":954,"passed_time":53.35138691,"remaining_time":2.513939697},
{"learn":[0.2462658363],"iteration":955,"passed_time":53.46763017,"remaining_time":2.460853271},
{"learn":[0.2455595675],"iteration":956,"passed_time":53.62709539,"remaining_time":2.409576909},
{"learn":[0.2454341405],"iteration":957,"passed_time":53.76765892,"remaining_time":2.357246007},
{"learn":[0.24530257],"iteration":958,"passed_time":53.87851042,"remaining_time":2.303460821},
{"learn":[0.2446077939],"iteration":959,"passed_time":53.97949679,"remaining_time":2.249145699},
{"learn":[0.2445399662],"iteration":960,"passed_time":54.03533727,"remaining_time":2.192901304},
{"learn":[0.2440878047],"iteration":961,"passed_time":54.09260278,"remaining_time":2.136714039},
{"learn":[0.2436399245],"iteration":962,"passed_time":54.17546768,"remaining_time":2.081508104},
{"learn":[0.2435754116],"iteration":963,"passed_time":54.22381616,"remaining_time":2.02495579},
{"learn":[0.2434963336],"iteration":964,"passed_time":54.27246966,"remaining_time":1.968431542},
{"learn":[0.2431551684],"iteration":965,"passed_time":54.32738607,"remaining_time":1.912144023},
{"learn":[0.242970242],"iteration":966,"passed_time":54.37950372,"remaining_time":1.855763829},
{"learn":[0.2429007018],"iteration":967,"passed_time":54.46591572,"remaining_time":1.80052614},
{"learn":[0.2423681754],"iteration":968,"passed_time":54.56914226,"remaining_time":1.745762033},
{"learn":[0.2422140239],"iteration":969,"passed_time":54.61628114,"remaining_time":1.689163334},
{"learn":[0.2421345337],"iteration":970,"passed_time":54.66392895,"remaining_time":1.63259932},
{"learn":[0.2417194879],"iteration":971,"passed_time":54.72629514,"remaining_time":1.576477638},
{"learn":[0.2412703285],"iteration":972,"passed_time":54.77530202,"remaining_time":1.519972409},
{"learn":[0.2411220853],"iteration":973,"passed_time":54.82557155,"remaining_time":1.463516284},
{"learn":[0.2409021466],"iteration":974,"passed_time":54.87451154,"remaining_time":1.407038757},
{"learn":[0.2406291515],"iteration":975,"passed_time":54.92854937,"remaining_time":1.350702034},
{"learn":[0.2404854474],"iteration":976,"passed_time":54.97796085,"remaining_time":1.294261105},
{"learn":[0.2402328132],"iteration":977,"passed_time":55.03160094,"remaining_time":1.237929674},
{"learn":[0.2399224877],"iteration":978,"passed_time":55.08584831,"remaining_time":1.181616767},
{"learn":[0.2397686446],"iteration":979,"passed_time":55.13431052,"remaining_time":1.125190011},
{"learn":[0.2395689128],"iteration":980,"passed_time":55.18000295,"remaining_time":1.068725847},
{"learn":[0.2393677987],"iteration":981,"passed_time":55.22576306,"remaining_time":1.012284863},
{"learn":[0.2391457787],"iteration":982,"passed_time":55.26996986,"remaining_time":0.9558387463},
{"learn":[0.2390219115],"iteration":983,"passed_time":55.31736183,"remaining_time":0.8994692981},
{"learn":[0.2389327857],"iteration":984,"passed_time":55.36470369,"remaining_time":0.8431173151},
{"learn":[0.2388306952],"iteration":985,"passed_time":55.40897322,"remaining_time":0.7867399848},
{"learn":[0.2386649303],"iteration":986,"passed_time":55.45798586,"remaining_time":0.7304496618},
{"learn":[0.2384835143],"iteration":987,"passed_time":55.49795379,"remaining_time":0.674064216},
{"learn":[0.2382921931],"iteration":988,"passed_time":55.54723984,"remaining_time":0.6178156099},
{"learn":[0.238230877],"iteration":989,"passed_time":55.59334832,"remaining_time":0.5615489729},
{"learn":[0.2376528166],"iteration":990,"passed_time":55.63981231,"remaining_time":0.5053060654},
{"learn":[0.2374988985],"iteration":991,"passed_time":55.68741437,"remaining_time":0.4490920514},
{"learn":[0.2374270742],"iteration":992,"passed_time":55.73237481,"remaining_time":0.392876761},
{"learn":[0.2371741356],"iteration":993,"passed_time":55.78126868,"remaining_time":0.3367078592},
{"learn":[0.2369784344],"iteration":994,"passed_time":55.82669692,"remaining_time":0.2805361654},
{"learn":[0.2367399078],"iteration":995,"passed_time":55.87148609,"remaining_time":0.2243834783},
{"learn":[0.2360467117],"iteration":996,"passed_time":55.92030292,"remaining_time":0.1682657059},
{"learn":[0.2359581507],"iteration":997,"passed_time":55.96551897,"remaining_time":0.1121553486},
{"learn":[0.2357550272],"iteration":998,"passed_time":56.01350861,"remaining_time":0.05606957819},
{"learn":[0.2355293056],"iteration":999,"passed_time":56.06489802,"remaining_time":0}
]}